Workbook

Sheet 0 — Assumptions
A1: DLOOP — FOGLIO ASSUNZIONI CENTRALIZZATE | Modifica qui, non nei fogli area
A2: 🔵 Celle gialle = input modificabili │ Tutti i fogli area si aggiorneranno automaticamente │ Non toccare i fogli area se non per i dati che non sono qui
A3: Assunzione | B3: Valore | C3: Unità | D3: Fonte / Note
A4: PRICING SaaS SMB
A5: Prezzo Starter | B5: € 39 | C5: €/mese | D5: 50 ordini/mese inclusi
A6: Prezzo Pro | B6: € 79 | C6: €/mese | D6: 500 ordini/mese inclusi
A7: Prezzo Enterprise | B7: € 149 | C7: €/mese | D7: Ordini illimitati
A9: PRICING B2B OPERATOR
A10: Starter Operator | B10: € 99 | C10: €/mese | D10: 500 ordini inclusi, €0.90/extra
A11: Business Operator | B11: € 199 | C11: €/mese | D11: 1.500 ordini inclusi, €0.60/extra — ADV target
A12: Enterprise Operator | B12: € 499 | C12: €/mese | D12: 5.000 ordini inclusi, €0.30/extra
A14: METRICHE SaaS — CRESCITA
A15: Churn rate mensile (M1-M6) | B15: 0.04 | C15: % merchant | D15: 4% early stage. Benchmark: 5-7% startup fase lancio
A16: Churn rate mensile (M7+) | B16: 0.02 | C16: % merchant | D16: 2% dopo product-market fit. Target <2%
A17: Expansion MRR mensile | B17: 0.03 | C17: % su MRR | D17: Up-sell Starter→Pro. Benchmark SaaS: 3-5%
A18: Tasso crescita merchant M1-M6 | B18: media +4 | C18: merchant/mese | D18: Guerriglia: warm network + outreach diretto
A19: Tasso crescita merchant M7+ | B19: media +5 | C19: merchant/mese | D19: Con Sales BDR attivo da M5
A21: UNIT ECONOMICS — CAC e LTV
A22: CAC Guerriglia M1-M4 | B22: € 45 | C22: €/merchant | D22: Budget mktg €170 ÷ ~4 nuovi merchant/mese
A23: CAC M5-M8 (con Sales hire) | B23: € 120 | C23: €/merchant | D23: (Sales €1.200 + Ads €200) ÷ ~12 new merchant
A24: CAC M9+ (a regime) | B24: € 85 | C24: €/merchant | D24: Scala con outbound + referral attivi
A25: Lifetime (durata media cliente) | B25: 24 | C25: mesi | D25: Con churn 2%/mese. LT = 1/churn = 50 mesi, conservativo 24
A26: ARPU medio atteso a regime | B26: € 120 | C26: €/mese | D26: Mix tier Starter/Pro/Enterprise
A27: LTV (ARPU × Lifetime) | B27: € 2.880 | C27: € | D27: €120 × 24 mesi
A28: LTV:CAC ratio (target >3x) | B28: 3.4 | C28: x | D28: €2.880 ÷ €85 CAC regime. Benchmark SaaS: >3x
A29: CAC Payback Period | B29: 12 | C29: mesi | D29: €85 ÷ €120 ARPU × (1-COGS%). Target <18 mesi
A31: IMPOSTE E FINANZIARI
A32: IRES | B32: 0.24 | C32: % | D32: Imposta sul Reddito delle Società
A33: IRAP | B33: 0.039 | C33: % | D33: Imposta Regionale Attività Produttive
A34: Aliquota totale | B34: 0.279 | C34: % | D34: IRES + IRAP. Solo su EBT > 0
A35: Tasso interesse conto deposito | B35: 0.025 | C35: % | D35: ~2.5% annuo su seed investito
A36: Seed round atteso | B36: € 75.000 | C36: € | D36: Range €50-100K via MoodCapital — ipotesi M3
A37: Cash runway target | B37: 16 | C37: mesi | D37: Con €75K seed. Target ≥15 mesi (FlowCog benchmark)
A39: COSTI — BENCHMARK VERIFICATI 2025-2026
A40: Supabase Pro | B40: 25 | C40: $/mese | D40: piano base. Overage su compute. Fonte: supabase.com/pricing
A41: Twilio per messaggio | B41: 0.005 | C41: $/msg | D41: + Meta fee. Da lug 2025 pricing per template. Fonte: twilio.com
A42: Commissione Stripe EU | B42: 1.50%+€0.25 | C42: /transaz | D42: Carte EU. Fonte: stripe.com/it/pricing
A43: Commercialista SRL min. | B43: € 141.50 | C43: €/mese | D43: FiscalSky online. Tradiz: €208-416/mese
A44: Benefits load (P.IVA) | B44: 0 | C44: % | D44: P.IVA: 0% carico azienda. CEO se dipendente: +25-28%
A46: BREAK-EVEN E OBIETTIVI
A47: N. merchant per break-even | B47: 61 | C47: merchant | D47: M11 target. €13.8K revenue vs €11.6K OpEx
A48: ARPU break-even | B48: € 226 | C48: €/mese | D48: Mix SMB+B2B. Fonte: pitch deck
A49: Gross Margin target | B49: 0.73 | C49: % | D49: Revenue – Infra – Var. Fonte: pitch deck
A50: Rule of 40 target | B50: 40 | C50: % | D50: Growth Rate % + EBITDA Margin %. Standard VC

Sheet MASTER
A1: DLOOP SRL — BUDGET MASTER GUERRIGLIA 18 MESI (ART. 2425 C.C.)
A2: 🟢 Celle verdi = differenziatori Guerriglia │ Tutti i valori provengono dai fogli area │ Non modificare direttamente
A3: Voce | B3: M1 | C3: M2 | D3: M3 | E3: M4 | F3: M5 | G3: M6 | H3: M7 | I3: M8 | J3: M9 | K3: M10 | L3: M11 | M3: M12 | N3: M13 | O3: M14 | P3: M15 | Q3: M16 | R3: M17 | S3: M18 | T3: TOTALE
A4: Fase ▶ | B4: OUTREACH | C4: OUTREACH | D4: OUTREACH | E4: OUTREACH | F4: HYBRID | G4: HYBRID | H4: HYBRID | I4: SCALE | J4: SCALE | K4: SCALE | L4: SCALE | M4: SCALE | N4: SCALE | O4: SCALE | P4: SCALE | Q4: SCALE | R4: SCALE | S4: SCALE
A5: A) VALORE DELLA PRODUZIONE
A6: A.1 Ricavi SaaS SMB | B6: ='A — Ricavi'!B16 -> 196 | C6: ='A — Ricavi'!C16 -> 353 | D6: ='A — Ricavi'!D16 -> 777 | E6: ='A — Ricavi'!E16 -> 1201 | F6: ='A — Ricavi'!F16 -> 1664 | G6: ='A — Ricavi'!G16 -> 2166 | H6: ='A — Ricavi'!H16 -> 2708 | I6: ='A — Ricavi'!I16 -> 3289 | ... S6: ='A — Ricavi'!S16 -> 10492 | T6: =SUM(B6:S6) -> 84472
A7: A.2 Ricavi WhatsApp Bot | B7: ='A — Ricavi'!B22 -> 0 | C7: ='A — Ricavi'!C22 -> 0 | D7: ='A — Ricavi'!D22 -> 0 | E7: ='A — Ricavi'!E22 -> 22 | F7: ='A — Ricavi'!F22 -> 43 | G7: ='A — Ricavi'!G22 -> 64 | H7: ='A — Ricavi'!H22 -> 116 | I7: ='A — Ricavi'!I22 -> 188 | ... S7: ='A — Ricavi'!S22 -> 1013 | T7: =SUM(B7:S7) -> 6923
A8: A.3 Ricavi B2B Operator | B8: ='A — Ricavi'!B28 -> 0 | C8: ='A — Ricavi'!C28 -> 0 | D8: ='A — Ricavi'!D28 -> 99 | E8: ='A — Ricavi'!E28 -> 298 | F8: ='A — Ricavi'!F28 -> 497 | G8: ='A — Ricavi'!G28 -> 795 | H8: ='A — Ricavi'!H28 -> 994 | I8: ='A — Ricavi'!I28 -> 1292 | ... S8: ='A — Ricavi'!S28 -> 5769 | T8: =SUM(B8:S8) -> 36989
A9: TOTALE VALORE PRODUZIONE (A) incl. fee ordini | B9: =B6+B7+B8+IF(ISNUMBER('A.4 — Fee per Ordine'!B39),'A.4 — Fee per Ordine'!B39,0) -> 196 | C9: =C6+C7+C8+IF(ISNUMBER('A.4 — Fee per Ordine'!C39),'A.4 — Fee per Ordine'!C39,0) -> 353 | D9: =D6+D7+D8+IF(ISNUMBER('A.4 — Fee per Ordine'!D39),'A.4 — Fee per Ordine'!D39,0) -> 1056 | E9: =E6+E7+E8+IF(ISNUMBER('A.4 — Fee per Ordine'!E39),'A.4 — Fee per Ordine'!E39,0) -> 2001 | F9: =F6+F7+F8+IF(ISNUMBER('A.4 — Fee per Ordine'!F39),'A.4 — Fee per Ordine'!F39,0) -> 2984 | G9: =G6+G7+G8+IF(ISNUMBER('A.4 — Fee per Ordine'!G39),'A.4 — Fee per Ordine'!G39,0) -> 4285 | H9: =H6+H7+H8+IF(ISNUMBER('A.4 — Fee per Ordine'!H39),'A.4 — Fee per Ordine'!H39,0) -> 5828 | I9: =I6+I7+I8+IF(ISNUMBER('A.4 — Fee per Ordine'!I39),'A.4 — Fee per Ordine'!I39,0) -> 7259 | ... S9: =S6+S7+S8+IF(ISNUMBER('A.4 — Fee per Ordine'!S39),'A.4 — Fee per Ordine'!S39,0) -> 30174 | T9: =SUM(B9:S9) -> 208964
A11: B) COSTI DELLA PRODUZIONE
A12: B.1 Infrastruttura Cloud & API | B12: ='B1 — Infrastruttura'!B18 -> 150 | C12: ='B1 — Infrastruttura'!C18 -> 175 | D12: ='B1 — Infrastruttura'!D18 -> 220 | E12: ='B1 — Infrastruttura'!E18 -> 277 | F12: ='B1 — Infrastruttura'!F18 -> 400 | G12: ='B1 — Infrastruttura'!G18 -> 513 | H12: ='B1 — Infrastruttura'!H18 -> 610 | I12: ='B1 — Infrastruttura'!I18 -> 733 | ... S12: ='B1 — Infrastruttura'!S18 -> 2565 | T12: =SUM(B12:S12) -> 20299
A13: B.2 Servizi Professionali | B13: ='B2 — Servizi'!B17 -> 267 | C13: ='B2 — Servizi'!C17 -> 272 | D13: ='B2 — Servizi'!D17 -> 292 | E13: ='B2 — Servizi'!E17 -> 327 | F13: ='B2 — Servizi'!F17 -> 357 | G13: ='B2 — Servizi'!G17 -> 387 | H13: ='B2 — Servizi'!H17 -> 427 | I13: ='B2 — Servizi'!I17 -> 467 | ... S13: ='B2 — Servizi'!S17 -> 1072 | T13: =SUM(B13:S13) -> 10706
A14: B.3 Marketing Guerriglia ★ | B14: ='B3 — Marketing'!B28 -> 170 | C14: ='B3 — Marketing'!C28 -> 180 | D14: ='B3 — Marketing'!D28 -> 220 | E14: ='B3 — Marketing'!E28 -> 230 | F14: ='B3 — Marketing'!F28 -> 310 | G14: ='B3 — Marketing'!G28 -> 390 | H14: ='B3 — Marketing'!H28 -> 470 | I14: ='B3 — Marketing'!I28 -> 550 | ... S14: ='B3 — Marketing'!S28 -> 1370 | T14: =SUM(B14:S14) -> 12520
A15: B.4 Personale e Collaboratori | B15: ='B4 — Personale'!B34 -> 3500 | C15: ='B4 — Personale'!C34 -> 3500 | D15: ='B4 — Personale'!D34 -> 3500 | E15: ='B4 — Personale'!E34 -> 5000 | F15: ='B4 — Personale'!F34 -> 6200 | G15: ='B4 — Personale'!G34 -> 6900 | H15: ='B4 — Personale'!H34 -> 9400 | I15: ='B4 — Personale'!I34 -> 9400 | ... S15: ='B4 — Personale'!S34 -> 13500 | T15: =SUM(B15:S15) -> 167000
A16: B.5 Ammortamenti | B16: ='B5 — Ammortamenti'!B14 -> 200 | C16: ='B5 — Ammortamenti'!C14 -> 200 | D16: ='B5 — Ammortamenti'!D14 -> 200 | E16: ='B5 — Ammortamenti'!E14 -> 200 | F16: ='B5 — Ammortamenti'!F14 -> 200 | G16: ='B5 — Ammortamenti'!G14 -> 200 | H16: ='B5 — Ammortamenti'!H14 -> 200 | I16: ='B5 — Ammortamenti'!I14 -> 200 | ... S16: ='B5 — Ammortamenti'!S14 -> 200 | T16: =SUM(B16:S16) -> 3600
A17: B.6 Costi Variabili | B17: ='B6 — Costi Variabili'!B16 -> 42 | C17: ='B6 — Costi Variabili'!C16 -> 77 | D17: ='B6 — Costi Variabili'!D16 -> 128 | E17: ='B6 — Costi Variabili'!E16 -> 198 | F17: ='B6 — Costi Variabili'!F16 -> 284 | G17: ='B6 — Costi Variabili'!G16 -> 384 | H17: ='B6 — Costi Variabili'!H16 -> 493 | I17: ='B6 — Costi Variabili'!I16 -> 614 | ... S17: ='B6 — Costi Variabili'!S16 -> 2142 | T17: =SUM(B17:S17) -> 16447
A18: TOTALE COSTI PRODUZIONE (B) | B18: =B12+B13+B14+B15+B16+B17 -> 4329 | C18: =C12+C13+C14+C15+C16+C17 -> 4404 | D18: =D12+D13+D14+D15+D16+D17 -> 4560 | E18: =E12+E13+E14+E15+E16+E17 -> 6232 | F18: =F12+F13+F14+F15+F16+F17 -> 7751 | G18: =G12+G13+G14+G15+G16+G17 -> 8774 | H18: =H12+H13+H14+H15+H16+H17 -> 11600 | I18: =I12+I13+I14+I15+I16+I17 -> 11964 | ... S18: =S12+S13+S14+S15+S16+S17 -> 20849 | T18: =SUM(B18:S18) -> 230572
A20: ▶ EBIT (A – B) | B20: =B9-B18 -> -4133 | C20: =C9-C18 -> -4051 | D20: =D9-D18 -> -3504 | E20: =E9-E18 -> -4231 | F20: =F9-F18 -> -4767 | G20: =G9-G18 -> -4489 | H20: =H9-H18 -> -5772 | I20: =I9-I18 -> -4705 | ... S20: =S9-S18 -> 9325 | T20: =SUM(B20:S20) -> -21608
A22: C/D) PROVENTI E ONERI FINANZIARI
A23: Proventi finanziari (interessi su seed) | B23: ='C-D — Finanziari'!B8 -> 0 | C23: ='C-D — Finanziari'!C8 -> 0 | D23: ='C-D — Finanziari'!D8 -> 0 | E23: ='C-D — Finanziari'!E8 -> 50 | F23: ='C-D — Finanziari'!F8 -> 50 | G23: ='C-D — Finanziari'!G8 -> 50 | H23: ='C-D — Finanziari'!H8 -> 80 | I23: ='C-D — Finanziari'!I8 -> 80 | ... S23: ='C-D — Finanziari'!S8 -> 150 | T23: =SUM(B23:S23) -> 1450
A24: Interessi passivi | B24: ='C-D — Finanziari'!B10 -> 0 | C24: ='C-D — Finanziari'!C10 -> 0 | D24: ='C-D — Finanziari'!D10 -> 0 | E24: ='C-D — Finanziari'!E10 -> 0 | F24: ='C-D — Finanziari'!F10 -> 0 | G24: ='C-D — Finanziari'!G10 -> 0 | H24: ='C-D — Finanziari'!H10 -> 0 | I24: ='C-D — Finanziari'!I10 -> 0 | ... S24: ='C-D — Finanziari'!S10 -> 0 | T24: =SUM(B24:S24) -> 0
A25: RISULTATO ANTE IMPOSTE (EBT) | B25: =B20+B23-B24 -> -4133 | C25: =C20+C23-C24 -> -4051 | D25: =D20+D23-D24 -> -3504 | E25: =E20+E23-E24 -> -4181 | F25: =F20+F23-F24 -> -4717 | G25: =G20+G23-G24 -> -4439 | H25: =H20+H23-H24 -> -5692 | I25: =I20+I23-I24 -> -4625 | ... S25: =S20+S23-S24 -> 9475 | T25: =SUM(B25:S25) -> -20158
A27: IMPOSTE (IRES 24% + IRAP 3,9%)
A28: Imposte stimate MAX(0; EBT × 27,9%) | B28: =MAX(0,B25*0.279) -> 0 | C28: =MAX(0,C25*0.279) -> 0 | D28: =MAX(0,D25*0.279) -> 0 | E28: =MAX(0,E25*0.279) -> 0 | F28: =MAX(0,F25*0.279) -> 0 | G28: =MAX(0,G25*0.279) -> 0 | H28: =MAX(0,H25*0.279) -> 0 | I28: =MAX(0,I25*0.279) -> 0 | ... S28: =MAX(0,S25*0.279) -> 2643.525 | T28: =SUM(B28:S28) -> 7006.527
A30: ▶▶ UTILE / PERDITA NETTA | B30: =B25-B28 -> -4133 | C30: =C25-C28 -> -4051 | D30: =D25-D28 -> -3504 | E30: =E25-E28 -> -4181 | F30: =F25-F28 -> -4717 | G30: =G25-G28 -> -4439 | H30: =H25-H28 -> -5692 | I30: =I25-I28 -> -4625 | ... S30: =S25-S28 -> 6831.475 | T30: =SUM(B30:S30) -> -27164.527
A32: ★ Verde = differenziatori Guerriglia │ Tutti i valori provengono dai fogli area sottostanti │ Non modificare le formule su questo foglio — modificare i dati nei fogli area

Sheet A — Ricavi
A1: A — RICAVI | Dettaglio per stream e tier
A2: 🔵 Input blu = modificabili │ Analisi per tier, ARPU, churn, B2B pipeline
A3: Voce | B3: M1 | C3: M2 | D3: M3 | E3: M4 | F3: M5 | G3: M6 | H3: M7 | I3: M8 | J3: M9 | K3: M10 | L3: M11 | M3: M12 | N3: M13 | O3: M14 | P3: M15 | Q3: M16 | R3: M17 | S3: M18 | T3: TOTALE
A4: A.1 RICAVI SaaS SMB — Subscription per Tier
A5: Merchant attivi per tier (input)
A6: Starter €39/mese — n. merchant | B6: 3 | C6: 5 | D6: 8 | E6: 11 | F6: 15 | G6: 20 | H6: 24 | I6: 29 | J6: 34 | K6: 38 | L6: 43 | M6: 48 | N6: 53 | O6: 57 | P6: 61 | Q6: 65 | R6: 68 | S6: 72 | T6: =SUM(B6:S6) -> 654
A7: Pro €79/mese — n. merchant | B7: 1 | C7: 2 | D7: 4 | E7: 6 | F7: 8 | G7: 10 | H7: 13 | I7: 16 | J7: 19 | K7: 23 | L7: 27 | M7: 31 | N7: 35 | O7: 38 | P7: 42 | Q7: 46 | R7: 49 | S7: 52 | T7: =SUM(B7:S7) -> 422
A8: Enterprise €149/mese — n. merchant | B8: 0 | C8: 0 | D8: 1 | E8: 2 | F8: 3 | G8: 4 | H8: 5 | I8: 6 | J8: 7 | K8: 8 | L8: 10 | M8: 12 | N8: 14 | O8: 16 | P8: 18 | Q8: 20 | R8: 22 | S8: 24 | T8: =SUM(B8:S8) -> 172
A9: Totale merchant attivi | B9: =SUM(B6:B8) -> 4 | C9: =SUM(C6:C8) -> 7 | D9: =SUM(D6:D8) -> 13 | E9: =SUM(E6:E8) -> 19 | F9: =SUM(F6:F8) -> 26 | G9: =SUM(G6:G8) -> 34 | H9: =SUM(H6:H8) -> 42 | I9: =SUM(I6:I8) -> 51 | ... S9: =SUM(S6:S8) -> 148 | T9: =SUM(B9:S9) -> 1248
A10: Nuovi merchant acquisiti (mese) | B10: 4 | C10: 3 | D10: 6 | E10: 6 | F10: 7 | G10: 8 | H10: 8 | I10: 9 | J10: 9 | K10: 9 | L10: 11 | M10: 11 | N10: 11 | O10: 9 | P10: 10 | Q10: 10 | R10: 8 | S10: 9 | T10: =SUM(B10:S10) -> 148
A11: Churn rate mensile (%) | B11: 5 | C11: 5 | D11: 4 | E11: 4 | F11: 4 | G11: 3 | H11: 3 | I11: 3 | J11: 3 | K11: 3 | L11: 2 | M11: 2 | N11: 2 | O11: 2 | P11: 2 | Q11: 2 | R11: 2 | S11: 2 | T11: =SUM(B11:S11) -> 53
A12: Revenue per tier (formula)
A13: Starter €39 × n | B13: =B6*39 -> 117 | C13: =C6*39 -> 195 | D13: =D6*39 -> 312 | E13: =E6*39 -> 429 | F13: =F6*39 -> 585 | G13: =G6*39 -> 780 | H13: =H6*39 -> 936 | I13: =I6*39 -> 1131 | ... S13: =S6*39 -> 2808 | T13: =SUM(B13:S13) -> 25506
A14: Pro €79 × n | B14: =B7*79 -> 79 | C14: =C7*79 -> 158 | D14: =D7*79 -> 316 | E14: =E7*79 -> 474 | F14: =F7*79 -> 632 | G14: =G7*79 -> 790 | H14: =H7*79 -> 1027 | I14: =I7*79 -> 1264 | ... S14: =S7*79 -> 4108 | T14: =SUM(B14:S14) -> 33338
A15: Enterprise €149 × n | B15: =B8*149 -> 0 | C15: =C8*149 -> 0 | D15: =D8*149 -> 149 | E15: =E8*149 -> 298 | F15: =F8*149 -> 447 | G15: =G8*149 -> 596 | H15: =H8*149 -> 745 | I15: =I8*149 -> 894 | ... S15: =S8*149 -> 3576 | T15: =SUM(B15:S15) -> 25628
A16: TOTALE Ricavi SMB (Starter+Pro+Enterprise) | B16: =B13+B14+B15 -> 196 | C16: =C13+C14+C15 -> 353 | D16: =D13+D14+D15 -> 777 | E16: =E13+E14+E15 -> 1201 | F16: =F13+F14+F15 -> 1664 | G16: =G13+G14+G15 -> 2166 | H16: =H13+H14+H15 -> 2708 | I16: =I13+I14+I15 -> 3289 | ... S16: =S13+S14+S15 -> 10492
A17: ARPU medio (Rev SMB ÷ Merchant)
A19: A.2 RICAVI WhatsApp Bot Add-on
A20: TOTALE A.2 WhatsApp Bot | B20: 0 | C20: 0 | D20: 0 | E20: 0 | F20: 0 | G20: 0 | H20: 0 | I20: 0 | J20: 0 | K20: 0 | L20: 0 | M20: 0 | N20: 0 | O20: 0 | P20: 0 | Q20: 0 | R20: 0 | S20: 0 | T20: =SUM(B19:S19) -> 0
A21: A.2.2 Extra conversazioni (overflow stimato) | B21: 0 | C21: 0 | D21: 0 | E21: 22 | F21: 43 | G21: 64 | H21: 116 | I21: 188 | J21: 260 | K21: 312 | L21: 415 | M21: 518 | N21: 621 | O21: 724 | P21: 827 | Q21: 869 | R21: 931 | S21: 1013 | T21: =SUM(B20:S20) -> 0
A22: TOTALE A.2 WhatsApp Bot | B22: =B20+B21 -> 0 | C22: =C20+C21 -> 0 | D22: =D20+D21 -> 0 | E22: =E20+E21 -> 22 | F22: =F20+F21 -> 43 | G22: =G20+G21 -> 64 | H22: =H20+H21 -> 116 | I22: =I20+I21 -> 188 | ... S22: =S20+S21 -> 1013
A24: A.3 RICAVI B2B Operator — Pipeline e Revenue
A25: A.3.1 Starter Operator €99/mese — n. clienti | B25: 0 | C25: 0 | D25: 1 | E25: 1 | F25: 1 | G25: 2 | H25: 2 | I25: 3 | J25: 3 | K25: 4 | L25: 4 | M25: 5 | N25: 5 | O25: 6 | P25: 7 | Q25: 8 | R25: 9 | S25: 10 | T25: =SUM(B24:S24) -> 0
A26: A.3.2 Business Operator €199/mese — n. clienti [ADV Advertising target] | B26: 0 | C26: 0 | D26: 0 | E26: 1 | F26: 2 | G26: 3 | H26: 4 | I26: 5 | J26: 6 | K26: 7 | L26: 8 | M26: 9 | N26: 11 | O26: 12 | P26: 14 | Q26: 15 | R26: 17 | S26: 19 | T26: =SUM(B25:S25) -> 71
A27: A.3.3 Enterprise Operator €499/mese — n. clienti | B27: 0 | C27: 0 | D27: 0 | E27: 0 | F27: 0 | G27: 0 | H27: 0 | I27: 0 | J27: 0 | K27: 0 | L27: 0 | M27: 0 | N27: 0 | O27: 1 | P27: 1 | Q27: 1 | R27: 2 | S27: 2 | T27: =SUM(B26:S26) -> 133
A28: TOTALE A.3 B2B Operator | B28: =B25*99+B26*199+B27*499 -> 0 | C28: =C25*99+C26*199+C27*499 -> 0 | D28: =D25*99+D26*199+D27*499 -> 99 | E28: =E25*99+E26*199+E27*499 -> 298 | F28: =F25*99+F26*199+F27*499 -> 497 | G28: =G25*99+G26*199+G27*499 -> 795 | H28: =H25*99+H26*199+H27*499 -> 994 | I28: =I25*99+I26*199+I27*499 -> 1292 | ... S28: =S25*99+S26*199+S27*499 -> 5769
A32: TOTALE RICAVI (A) → Alimenta il Master | B32: =B16+B22+B28 -> 196 | C32: =C16+C22+C28 -> 353 | D32: =D16+D22+D28 -> 876 | E32: =E16+E22+E28 -> 1521 | F32: =F16+F22+F28 -> 2204 | G32: =G16+G22+G28 -> 3025 | H32: =H16+H22+H28 -> 3818 | I32: =I16+I22+I28 -> 4769 | ... S32: =S16+S22+S28 -> 17274 | T32: =SUM(B31:S31) -> 0
A34: ★ Questo foglio alimenta il Master tramite riferimenti diretti. Modificare qui i dati merchant/tier, mai nel Master.

Sheet A.4 — Fee per Ordine
A1: A.4 — RICAVI FEE PER ORDINE | Canone base + overage per ordine extra
A2: Giallo=modificabile | Verde=Business Plus NUOVO | Switch B5 (B2B) / B6 (SMB)
A3: Voce | B3: M1 | C3: M2 | D3: M3 | E3: M4 | F3: M5 | G3: M6 | H3: M7 | I3: M8 | J3: M9 | K3: M10 | L3: M11 | M3: M12 | N3: M13 | O3: M14 | P3: M15 | Q3: M16 | R3: M17 | S3: M18 | T3: TOTALE
A4: ⚙️ SWITCH — B5=B2B fee (1=ON) | B6=SMB fee (0=OFF Phase1)
A5: Switch B2B fee overage | B5: 1 | C5: 1=ON → fee B2B attive. 0=OFF → solo canone flat.
A6: Switch SMB fee overage (Phase 2) | B6: 0 | C6: 0=Phase1 puro. 1=Phase2 → fee SMB attive.
A7: 📐 PARAMETRI — Pricing confermato (celle gialle = modificabili)
A8: SMB Starter: fee extra/ordine (oltre 50 inclusi) | B8: 0.8 | C8: €0,80/ord ✓ confermato
A9: SMB Pro: fee extra/ordine (oltre 100 inclusi) | B9: 0.8 | C9: €0,80/ord ✓ confermato
A10: SMB Enterprise: fee extra/ordine (oltre 250 inclusi) | B10: 0.5 | C10: €0,50/ord ✓ confermato
A11: Soglia SMB Starter (ordini inclusi nel canone) | B11: 50 | C11: 50 ordini/mese ✓
A12: Soglia SMB Pro (ordini inclusi nel canone) | B12: 100 | C12: 100 ordini/mese ✓ (era 500 → CORRETTO!)
A13: Soglia SMB Enterprise (ordini inclusi nel canone) | B13: 250 | C13: 250 ordini/mese ✓
A14: B2B Starter: fee extra/ordine (oltre 500 inclusi) | B14: 0.9 | C14: €0,90/ord ✓
A15: B2B Business: fee extra/ordine (oltre 1.500 inclusi) | B15: 0.6 | C15: €0,60/ord ✓ −33% vs Starter
A16: B2B Business Plus: fee extra/ordine (oltre 3.000) ★ | B16: 0.45 | C16: €0,45/ord ✓ −25% vs Business NUOVO TIER
A17: B2B Enterprise: fee extra/ordine (oltre 5.000 inclusi) | B17: 0.3 | C17: €0,30/ord ✓ −33% vs Business Plus
A18: Soglia B2B Starter (ordini inclusi) | B18: 500 | C18: 500 ordini/mese inclusi nel canone
A19: Soglia B2B Business (ordini inclusi) | B19: 1500 | C19: 1.500 ordini/mese inclusi nel canone
A20: Soglia B2B Business Plus (ordini inclusi) ★ | B20: 3000 | C20: 3.000 ordini/mese copre fascia 2K-4K NUOVO
A21: 💼 B2B OPERATOR — 4 TIER (canone + overage per ordine extra oltre soglia inclusa)
A22: N. clienti B2B Starter attivi | B22: 0 | C22: 0 | D22: 1 | E22: 1 | F22: 1 | G22: 2 | H22: 2 | I22: 3 | J22: 3 | K22: 4 | L22: 4 | M22: 5 | N22: 5 | O22: 6 | P22: 7 | Q22: 8 | R22: 9 | S22: 10 | T22: =SUM(B22:S22) -> 71
A23: A.4.1 B2B Starter (700−500=200 extra × €0,90 × switch) | B23: =$B$5*MAX(0,700-$B$18)*$B$14*B22 -> 0 | C23: =$B$5*MAX(0,700-$B$18)*$B$14*C22 -> 0 | D23: =$B$5*MAX(0,700-$B$18)*$B$14*D22 -> 180 | E23: =$B$5*MAX(0,700-$B$18)*$B$14*E22 -> 180 | F23: =$B$5*MAX(0,700-$B$18)*$B$14*F22 -> 180 | G23: =$B$5*MAX(0,700-$B$18)*$B$14*G22 -> 360 | H23: =$B$5*MAX(0,700-$B$18)*$B$14*H22 -> 360 | I23: =$B$5*MAX(0,700-$B$18)*$B$14*I22 -> 540 | ... S23: =$B$5*MAX(0,700-$B$18)*$B$14*S22 -> 1800 | T23: =SUM(B23:S23) -> 12780
A24: N. clienti B2B Business attivi | B24: 0 | C24: 0 | D24: 0 | E24: 1 | F24: 2 | G24: 3 | H24: 4 | I24: 5 | J24: 6 | K24: 7 | L24: 8 | M24: 9 | N24: 11 | O24: 12 | P24: 14 | Q24: 15 | R24: 17 | S24: 19 | T24: =SUM(B24:S24) -> 133
A25: A.4.2 B2B Business (2.000−1.500=500 extra × €0,60 × switch) | B25: =$B$5*MAX(0,2000-$B$19)*$B$15*B24 -> 0 | C25: =$B$5*MAX(0,2000-$B$19)*$B$15*C24 -> 0 | D25: =$B$5*MAX(0,2000-$B$19)*$B$15*D24 -> 0 | E25: =$B$5*MAX(0,2000-$B$19)*$B$15*E24 -> 300 | F25: =$B$5*MAX(0,2000-$B$19)*$B$15*F24 -> 600 | G25: =$B$5*MAX(0,2000-$B$19)*$B$15*G24 -> 900 | H25: =$B$5*MAX(0,2000-$B$19)*$B$15*H24 -> 1200 | I25: =$B$5*MAX(0,2000-$B$19)*$B$15*I24 -> 1500 | ... S25: =$B$5*MAX(0,2000-$B$19)*$B$15*S24 -> 5700 | T25: =SUM(B25:S25) -> 39900
A26: N. clienti B2B Business Plus attivi ★NUOVO | B26: 0 | C26: 0 | D26: 0 | E26: 0 | F26: 0 | G26: 0 | H26: 1 | I26: 1 | J26: 2 | K26: 2 | L26: 3 | M26: 3 | N26: 4 | O26: 4 | P26: 5 | Q26: 6 | R26: 7 | S26: 8 | T26: =SUM(B26:S26) -> 46
A27: A.4.3 B2B Business Plus (4.000−3.000=1.000 extra × €0,45) ★NUOVO | B27: =$B$5*MAX(0,4000-$B$20)*$B$16*B26 -> 0 | C27: =$B$5*MAX(0,4000-$B$20)*$B$16*C26 -> 0 | D27: =$B$5*MAX(0,4000-$B$20)*$B$16*D26 -> 0 | E27: =$B$5*MAX(0,4000-$B$20)*$B$16*E26 -> 0 | F27: =$B$5*MAX(0,4000-$B$20)*$B$16*F26 -> 0 | G27: =$B$5*MAX(0,4000-$B$20)*$B$16*G26 -> 0 | H27: =$B$5*MAX(0,4000-$B$20)*$B$16*H26 -> 450 | I27: =$B$5*MAX(0,4000-$B$20)*$B$16*I26 -> 450 | ... S27: =$B$5*MAX(0,4000-$B$20)*$B$16*S26 -> 3600 | T27: =SUM(B27:S27) -> 20700
A28: N. clienti B2B Enterprise attivi | B28: 0 | C28: 0 | D28: 0 | E28: 0 | F28: 0 | G28: 0 | H28: 0 | I28: 0 | J28: 0 | K28: 0 | L28: 0 | M28: 0 | N28: 1 | O28: 1 | P28: 2 | Q28: 2 | R28: 3 | S28: 3 | T28: =SUM(B28:S28) -> 12
A29: A.4.4 B2B Enterprise (7.000−5.000=2.000 extra × €0,30 × switch) | B29: =$B$5*MAX(0,7000-5000)*$B$17*B28 -> 0 | C29: =$B$5*MAX(0,7000-5000)*$B$17*C28 -> 0 | D29: =$B$5*MAX(0,7000-5000)*$B$17*D28 -> 0 | E29: =$B$5*MAX(0,7000-5000)*$B$17*E28 -> 0 | F29: =$B$5*MAX(0,7000-5000)*$B$17*F28 -> 0 | G29: =$B$5*MAX(0,7000-5000)*$B$17*G28 -> 0 | H29: =$B$5*MAX(0,7000-5000)*$B$17*H28 -> 0 | I29: =$B$5*MAX(0,7000-5000)*$B$17*I28 -> 0 | ... S29: =$B$5*MAX(0,7000-5000)*$B$17*S28 -> 1800 | T29: =SUM(B29:S29) -> 7200
A30: SUBTOTALE Fee B2B Operator (4 tier) | B30: =B23+B25+B27+B29 -> 0 | C30: =C23+C25+C27+C29 -> 0 | D30: =D23+D25+D27+D29 -> 180 | E30: =E23+E25+E27+E29 -> 480 | F30: =F23+F25+F27+F29 -> 780 | G30: =G23+G25+G27+G29 -> 1260 | H30: =H23+H25+H27+H29 -> 2010 | I30: =I23+I25+I27+I29 -> 2490 | ... S30: =S23+S25+S27+S29 -> 12900 | T30: =SUM(B30:S30) -> 80580
A32: 🛒 SMB (switch B6=0 → Phase1 puro | B6=1 → Phase2 ibrida)
A33: N. merchant SMB Starter | B33: 3 | C33: 5 | D33: 8 | E33: 11 | F33: 15 | G33: 20 | H33: 24 | I33: 29 | J33: 34 | K33: 38 | L33: 43 | M33: 48 | N33: 53 | O33: 57 | P33: 61 | Q33: 65 | R33: 68 | S33: 72 | T33: =SUM(B33:S33) -> 654
A34: A.4.5 SMB Starter (80−50=30 extra × €0,80 × switch B6) [Phase 2] | B34: =$B$6*MAX(0,80-$B$11)*$B$8*B33 -> 0 | C34: =$B$6*MAX(0,80-$B$11)*$B$8*C33 -> 0 | D34: =$B$6*MAX(0,80-$B$11)*$B$8*D33 -> 0 | E34: =$B$6*MAX(0,80-$B$11)*$B$8*E33 -> 0 | F34: =$B$6*MAX(0,80-$B$11)*$B$8*F33 -> 0 | G34: =$B$6*MAX(0,80-$B$11)*$B$8*G33 -> 0 | H34: =$B$6*MAX(0,80-$B$11)*$B$8*H33 -> 0 | I34: =$B$6*MAX(0,80-$B$11)*$B$8*I33 -> 0 | ... S34: =$B$6*MAX(0,80-$B$11)*$B$8*S33 -> 0 | T34: =SUM(B34:S34) -> 0
A35: N. merchant SMB Pro | B35: 1 | C35: 2 | D35: 4 | E35: 6 | F35: 8 | G35: 10 | H35: 13 | I35: 16 | J35: 19 | K35: 23 | L35: 27 | M35: 31 | N35: 35 | O35: 38 | P35: 42 | Q35: 46 | R35: 49 | S35: 52 | T35: =SUM(B35:S35) -> 422
A36: A.4.6 SMB Pro (200−100=100 extra × €0,80 × switch B6) [Phase 2] | B36: =$B$6*MAX(0,200-$B$12)*$B$9*B35 -> 0 | C36: =$B$6*MAX(0,200-$B$12)*$B$9*C35 -> 0 | D36: =$B$6*MAX(0,200-$B$12)*$B$9*D35 -> 0 | E36: =$B$6*MAX(0,200-$B$12)*$B$9*E35 -> 0 | F36: =$B$6*MAX(0,200-$B$12)*$B$9*F35 -> 0 | G36: =$B$6*MAX(0,200-$B$12)*$B$9*G35 -> 0 | H36: =$B$6*MAX(0,200-$B$12)*$B$9*H35 -> 0 | I36: =$B$6*MAX(0,200-$B$12)*$B$9*I35 -> 0 | ... S36: =$B$6*MAX(0,200-$B$12)*$B$9*S35 -> 0 | T36: =SUM(B36:S36) -> 0
A37: SUBTOTALE Fee SMB → €0 mentre switch=0 | B37: =B34+B36 -> 0 | C37: =C34+C36 -> 0 | D37: =D34+D36 -> 0 | E37: =E34+E36 -> 0 | F37: =F34+F36 -> 0 | G37: =G34+G36 -> 0 | H37: =H34+H36 -> 0 | I37: =I34+I36 -> 0 | ... S37: =S34+S36 -> 0 | T37: =SUM(B37:S37) -> 0
A39: TOTALE A.4 Fee per Ordine → Alimenta il MASTER | B39: =B30+B37 -> 0 | C39: =C30+C37 -> 0 | D39: =D30+D37 -> 180 | E39: =E30+E37 -> 480 | F39: =F30+F37 -> 780 | G39: =G30+G37 -> 1260 | H39: =H30+H37 -> 2010 | I39: =I30+I37 -> 2490 | ... S39: =S30+S37 -> 12900 | T39: =SUM(B39:S39) -> 80580
A41: ✅ PRICING CONFERMATO — SMB: €39/50/€0,80 | €79/100/€0,80 | €149/250/€0,50 — B2B: €99/500/€0,90 | €199/1.500/€0,60 | ★€299/3.000/€0,45 | €499/5.000/€0,30

Sheet B1 — Infrastruttura
A1: B1 — INFRASTRUTTURA CLOUD & API | Costi verificati vs benchmark mercato 2026
A2: 🔵 Blu = input │ Benchmark: Supabase Pro $25/mese, Firebase free tier fino 10K MAU, Twilio $0.005/msg
A3: Voce | B3: M1 | C3: M2 | D3: M3 | E3: M4 | F3: M5 | G3: M6 | H3: M7 | I3: M8 | J3: M9 | K3: M10 | L3: M11 | M3: M12 | N3: M13 | O3: M14 | P3: M15 | Q3: M16 | R3: M17 | S3: M18 | T3: TOTALE
A4: Supabase (PostgreSQL + PostGIS + Realtime + Storage)
A5: Piano Pro $25/mese (base, produzione) [M1-M3: base plan, scala con volume ordini] | B5: 30 | C5: 35 | D5: 50 | E5: 65 | F5: 95 | G5: 130 | H5: 150 | I5: 175 | J5: 215 | K5: 255 | L5: 305 | M5: 365 | N5: 430 | O5: 490 | P5: 545 | Q5: 600 | R5: 650 | S5: 700 | T5: =SUM(B5:S5) -> 5285
A6: Benchmark: Pro Plan $25 + compute overage. Free tier NON usabile in produzione (auto-pause 7gg). Fonte: supabase.com/pricing 2026
A7: Firebase (Push notifications, Auth)
A8: Spark (free) → Blaze pay-as-you-go [M1-M2 free tier (10K MAU), da M3 uso marginale] | B8: 10 | C8: 10 | D8: 15 | E8: 20 | F8: 35 | G8: 45 | H8: 60 | I8: 80 | J8: 100 | K8: 125 | L8: 150 | M8: 180 | N8: 210 | O8: 245 | P8: 280 | Q8: 315 | R8: 345 | S8: 375 | T8: =SUM(B8:S8) -> 2600
A9: Benchmark: Free tier copre 10K MAU/mese. Spark gratuito M1-M2. Da M3 uso Blaze marginale. Fonte: firebase.google.com/pricing
A10: Google Maps API (Geocoding, Routing, Places)
A11: API calls (geocoding ordini + routing rider) [Da mar 2025: SKU-based, no credit $200 globale] | B11: 60 | C11: 75 | D11: 90 | E11: 110 | F11: 140 | G11: 170 | H11: 205 | I11: 245 | J11: 290 | K11: 335 | L11: 385 | M11: 445 | N11: 510 | O11: 560 | P11: 615 | Q11: 665 | R11: 715 | S11: 760 | T11: =SUM(B11:S11) -> 6375
A12: Attenzione: Da marzo 2025 Google ha eliminato il credit $200 mensile globale. SKU-based. A basso volume (M1-M4) stima €60-90. Fonte: scrap.io/google-maps-api 2025
A13: Twilio / WhatsApp Business API
A14: Twilio fee ($0.005/msg) + Meta template fee [Da lug 2025: Meta fattura per template. Utility msg free in 24h window] | B14: 20 | C14: 25 | D14: 35 | E14: 50 | F14: 95 | G14: 130 | H14: 155 | I14: 190 | J14: 230 | K14: 270 | L14: 315 | M14: 370 | N14: 425 | O14: 475 | P14: 525 | Q14: 570 | R14: 610 | S14: 650 | T14: =SUM(B14:S14) -> 5140
A15: Da luglio 2025 Meta addebita per template message. Utility templates GRATUITI nella finestra 24h. €20 M1 = ~4.000 messaggi. Fonte: twilio.com/whatsapp/pricing
A16: Dev Tools (GitHub, CI/CD, monitoring, domini)
A17: GitHub Teams + Vercel/Railway + dominio + monitoring | B17: 30 | C17: 30 | D17: 30 | E17: 32 | F17: 35 | G17: 38 | H17: 40 | I17: 43 | J17: 45 | K17: 48 | L17: 52 | M17: 56 | N17: 60 | O17: 64 | P17: 68 | Q17: 72 | R17: 76 | S17: 80 | T17: =SUM(B17:S17) -> 899
A18: TOTALE B1 Infrastruttura → Alimenta il Master | B18: =B5+B8+B11+B14+B17 -> 150 | C18: =C5+C8+C11+C14+C17 -> 175 | D18: =D5+D8+D11+D14+D17 -> 220 | E18: =E5+E8+E11+E14+E17 -> 277 | F18: =F5+F8+F11+F14+F17 -> 400 | G18: =G5+G8+G11+G14+G17 -> 513 | H18: =H5+H8+H11+H14+H17 -> 610 | I18: =I5+I8+I11+I14+I17 -> 733 | ... S18: =S5+S8+S11+S14+S17 -> 2565 | T18: =SUM(B18:S18) -> 20299
A19: ★ Tutti i costi sono stati verificati vs benchmark reali 2025/2026. Fonte per ogni voce indicata sopra.

Sheet B2 — Servizi
A1: B2 — SERVIZI PROFESSIONALI & CONFORMITÀ | Costi verificati vs mercato Italia 2026
A2: 🔵 Blu = input │ Commercialista SRL: €141-250/mese. Iubenda: €9/mese. Stripe EU: 1,5%+€0,25
A3: Voce | B3: M1 | C3: M2 | D3: M3 | E3: M4 | F3: M5 | G3: M6 | H3: M7 | I3: M8 | J3: M9 | K3: M10 | L3: M11 | M3: M12 | N3: M13 | O3: M14 | P3: M15 | Q3: M16 | R3: M17 | S3: M18 | T3: TOTALE
A4: Commercialista / CAF — Contabilità SRL ordinaria
A5: Tenuta contabilità ordinaria (SRL — obbligatoria) [€150/mese → €325/mese con crescita volume fatture] | B5: 150 | C5: 150 | D5: 160 | E5: 160 | F5: 175 | G5: 175 | H5: 195 | I5: 195 | J5: 210 | K5: 210 | L5: 240 | M5: 240 | N5: 265 | O5: 265 | P5: 285 | Q5: 295 | R5: 315 | S5: 325 | T5: =SUM(B5:S5) -> 4010
A6: Benchmark: SRL online da €141,50/mese (FiscalSky). Tradizionale €2.500-5.000/anno = €208-416/mese. Fonte: commercialista-startup.it, soluzionetasse.com 2026
A7: Consulenza Legale — GDPR, Contratti, TOS
A8: Consulenze spot (contratti rider P.IVA, GDPR, TOS BlaBlaCar-style) [€50-€220/mese. Setup iniziale GDPR/TOS una tantum] | B8: 50 | C8: 50 | D8: 50 | E8: 70 | F8: 70 | G8: 80 | H8: 80 | I8: 100 | J8: 100 | K8: 120 | L8: 150 | M8: 150 | N8: 180 | O8: 180 | P8: 200 | Q8: 200 | R8: 220 | S8: 220 | T8: =SUM(B8:S8) -> 2270
A9: Note: Setup iniziale privacy/TOS (Iubenda + avvocato) ~€500-1.500 una tantum già sostenuto. Mensile = solo consulenze spot. Fonte: lexdo.it 2025
A10: Iubenda — Privacy Policy, Cookie Law, TOS
A11: Piano Essential €129/anno = €10,75/mese [Benchmark verificato: iubenda.com/pricing] | B11: 9 | C11: 9 | D11: 9 | E11: 9 | F11: 9 | G11: 9 | H11: 9 | I11: 9 | J11: 9 | K11: 9 | L11: 9 | M11: 9 | N11: 9 | O11: 9 | P11: 9 | Q11: 9 | R11: 9 | S11: 9 | T11: =SUM(B11:S11) -> 162
A12: Commissioni Gateway Stripe — Elaborazione Pagamenti
A13: Fee mensili gateway (1,5%+€0,25/transaz EU + fee flat) [A regime: % su pagamenti subscription merchants. Cresce con volume.] | B13: 15 | C13: 20 | D13: 30 | E13: 45 | F13: 60 | G13: 80 | H13: 100 | I13: 120 | J13: 145 | K13: 170 | L13: 200 | M13: 240 | N13: 285 | O13: 320 | P13: 360 | Q13: 395 | R13: 430 | S13: 475 | T13: =SUM(B13:S13) -> 3490
A14: Stripe EU: 1,5% + €0,25/transazione (carte EU). Su €1.000 MRR = €15+oneri fissi. Fonte: stripe.com/it/pricing
A15: Costi fissi annuali SRL (quota mensile)
A16: Diritto camerale + vidimazione libri sociali (€309+€200/anno ÷ 12) [€519/anno = €43/mese. Fisso indipendente dal fatturato.] | B16: 43 | C16: 43 | D16: 43 | E16: 43 | F16: 43 | G16: 43 | H16: 43 | I16: 43 | J16: 43 | K16: 43 | L16: 43 | M16: 43 | N16: 43 | O16: 43 | P16: 43 | Q16: 43 | R16: 43 | S16: 43 | T16: =SUM(B16:S16) -> 774
A17: TOTALE B2 Servizi → Alimenta il Master | B17: =B5+B8+B11+B13+B16 -> 267 | C17: =C5+C8+C11+C13+C16 -> 272 | D17: =D5+D8+D11+D13+D16 -> 292 | E17: =E5+E8+E11+E13+E16 -> 327 | F17: =F5+F8+F11+F13+F16 -> 357 | G17: =G5+G8+G11+G13+G16 -> 387 | H17: =H5+H8+H11+H13+H16 -> 427 | I17: =I5+I8+I11+I13+I16 -> 467 | ... S17: =S5+S8+S11+S13+S16 -> 1072 | T17: =SUM(B17:S17) -> 10706

Sheet B3 — Marketing
A1: B3 — MARKETING GUERRIGLIA ★ | Zero paid ads M1-M4 — CEO fa outreach diretto
A2: 🟢 Verde = differenziatori vs Conservative/Normal │ Benchmark: 8% ARR mediana B2B SaaS (SaaS Capital 2025)
A3: Voce | B3: M1 | C3: M2 | D3: M3 | E3: M4 | F3: M5 | G3: M6 | H3: M7 | I3: M8 | J3: M9 | K3: M10 | L3: M11 | M3: M12 | N3: M13 | O3: M14 | P3: M15 | Q3: M16 | R3: M17 | S3: M18 | T3: TOTALE
A4: STRATEGIA GUERRIGLIA: M1-M4 = ZERO Google Ads, ZERO Meta Ads. Solo outreach diretto (CEO), social organico gratuito, micro-boost €80-100/mese e materiali fisici. Paid ads solo da M5 come supporto al Sales hire.
A5: 🚫 PAID ADS — Zero M1-M4, piccolo budget da M5 ★ GUERRIGLIA
A6: Google Ads (ZERO M1-M4 — €150 da M5, scala gradualmente) ★ [Benchmark: 8% ARR da M5] | B6: 0 | C6: 0 | D6: 0 | E6: 0 | F6: 150 | G6: 200 | H6: 250 | I6: 300 | J6: 350 | K6: 400 | L6: 450 | M6: 500 | N6: 550 | O6: 600 | P6: 650 | Q6: 700 | R6: 750 | S6: 800 | T6: =SUM(B6:S6) -> 6650
A7: Conservative spende €200+ da M1, Normal €350+ da M1. Guerriglia: €0 per 4 mesi → risparmio ~€1.400 vs Conservative
A8: 📱 SOCIAL MEDIA — Organico gratuito + micro-boost ★ GUERRIGLIA
A9: Social Boost (€80-100 post sponsorizzati mirati — solo M1-M4) ★ [Solo M1-M4, poi organico puro] | B9: 80 | C9: 80 | D9: 90 | E9: 100 | F9: 0 | G9: 0 | H9: 0 | I9: 0 | J9: 0 | K9: 0 | L9: 0 | M9: 0 | N9: 0 | O9: 0 | P9: 0 | Q9: 0 | R9: 0 | S9: 0 | T9: =SUM(B9:S9) -> 350
A10: Social Organico (CEO + team — COSTO ZERO) ★ [€0 — post, storie, gruppi WhatsApp di categoria delivery] | B10: 0 | C10: 0 | D10: 0 | E10: 0 | F10: 0 | G10: 0 | H10: 0 | I10: 0 | J10: 0 | K10: 0 | L10: 0 | M10: 0 | N10: 0 | O10: 0 | P10: 0 | Q10: 0 | R10: 0 | S10: 0 | T10: =SUM(B10:S10) -> 0
A11: 🤝 OUTREACH DIRETTO — Cuore del Guerriglia ★ GUERRIGLIA
A12: Materiali outreach (biglietti da visita, demo kit, telefonate, trasferte Campania) ★ [Costo principale M1-M4 del budget Guerriglia] | B12: 60 | C12: 70 | D12: 80 | E12: 80 | F12: 80 | G12: 90 | H12: 100 | I12: 100 | J12: 120 | K12: 120 | L12: 140 | M12: 150 | N12: 160 | O12: 170 | P12: 180 | Q12: 190 | R12: 200 | S12: 210 | T12: =SUM(B12:S12) -> 2300
A13: CEO chiama direttamente i contatti: Mario Cucciolito + rete personale + gruppi WhatsApp merchant Napoli/Caserta. Costo = spostamenti, materiali, caffè.
A14: 🎙️ PR & EVENTI LOCALI — Networking fisico ★ GUERRIGLIA
A15: Fiere locali, eventi Confartigianato/CNA, networking Pomigliano d'Arco / NA ★ [Costo basso, alto ritorno relazionale] | B15: 30 | C15: 30 | D15: 50 | E15: 50 | F15: 80 | G15: 100 | H15: 120 | I15: 150 | J15: 170 | K15: 180 | L15: 200 | M15: 220 | N15: 250 | O15: 270 | P15: 300 | Q15: 320 | R15: 340 | S15: 360 | T15: =SUM(B15:S15) -> 3220
A17: 📊 KPI MARKETING GUERRIGLIA
A18: CAC stimato (Budget mktg ÷ nuovi merchant stimati) | B18: =IF(B6>0,(B6+B9+B10+B12+B15)/MAX(1,B6/100),(B9+B10+B12+B15)/MAX(1,1)) -> 170 | C18: =IF(B6>0,(C6+C9+C10+C12+C15)/MAX(1,C6/100),(C9+C10+C12+C15)/MAX(1,1)) -> 180 | D18: =IF(B6>0,(D6+D9+D10+D12+D15)/MAX(1,D6/100),(D9+D10+D12+D15)/MAX(1,1)) -> 220 | E18: =IF(B6>0,(E6+E9+E10+E12+E15)/MAX(1,E6/100),(E9+E10+E12+E15)/MAX(1,1)) -> 230 | F18: =IF(B6>0,(F6+F9+F10+F12+F15)/MAX(1,F6/100),(F9+F10+F12+F15)/MAX(1,1)) -> 160 | G18: =IF(B6>0,(G6+G9+G10+G12+G15)/MAX(1,G6/100),(G9+G10+G12+G15)/MAX(1,1)) -> 190 | H18: =IF(B6>0,(H6+H9+H10+H12+H15)/MAX(1,H6/100),(H9+H10+H12+H15)/MAX(1,1)) -> 220 | I18: =IF(B6>0,(I6+I9+I10+I12+I15)/MAX(1,I6/100),(I9+I10+I12+I15)/MAX(1,1)) -> 250 | J18: =IF(B6>0,(J6+J9+J10+J12+J15)/MAX(1,J6/100),(J9+J10+J12+J15)/MAX(1,1)) -> 290 | K18: =IF(B6>0,(K6+K9+K10+K12+K15)/MAX(1,K6/100),(K9+K10+K12+K15)/MAX(1,1)) -> 300 | L18: =IF(B6>0,(L6+L9+L10+L12+L15)/MAX(1,L6/100),(L9+L10+L12+L15)/MAX(1,1)) -> 340 | M18: =IF(B6>0,(M6+M9+M10+M12+M15)/MAX(1,M6/100),(M9+M10+M12+M15)/MAX(1,1)) -> 370 | N18: =IF(B6>0,(N6+N9+N10+N12+N15)/MAX(1,N6/100),(N9+N10+N12+N15)/MAX(1,1)) -> 410 | O18: =IF(B6>0,(O6+O9+O10+O12+O15)/MAX(1,O6/100),(O9+O10+O12+O15)/MAX(1,1)) -> 440 | P18: =IF(B6>0,(P6+P9+P10+P12+P15)/MAX(1,P6/100),(P9+P10+P12+P15)/MAX(1,1)) -> 480 | Q18: =IF(B6>0,(Q6+Q9+Q10+Q12+Q15)/MAX(1,Q6/100),(Q9+Q10+Q12+Q15)/MAX(1,1)) -> 510 | R18: =IF(B6>0,(R6+R9+R10+R12+R15)/MAX(1,R6/100),(R9+R10+R12+R15)/MAX(1,1)) -> 540 | S18: =IF(B6>0,(S6+S9+S10+S12+S15)/MAX(1,S6/100),(S9+S10+S12+S15)/MAX(1,1)) -> 570 | T18: AVG
A19: % Marketing su Revenue (benchmark: 8% ARR mediana B2B SaaS) | B19: =IF('A — Ricavi'!B31>0,B26/'A — Ricavi'!B31,0) -> 0 | C19: =IF('A — Ricavi'!C31>0,C26/'A — Ricavi'!C31,0) -> 0 | D19: =IF('A — Ricavi'!D31>0,D26/'A — Ricavi'!D31,0) -> 0 | E19: =IF('A — Ricavi'!E31>0,E26/'A — Ricavi'!E31,0) -> 0 | F19: =IF('A — Ricavi'!F31>0,F26/'A — Ricavi'!F31,0) -> 0 | G19: =IF('A — Ricavi'!G31>0,G26/'A — Ricavi'!G31,0) -> 0 | H19: =IF('A — Ricavi'!H31>0,H26/'A — Ricavi'!H31,0) -> 0 | I19: =IF('A — Ricavi'!I31>0,I26/'A — Ricavi'!I31,0) -> 0 | ... S19: =IF('A — Ricavi'!S31>0,S26/'A — Ricavi'!S31,0) -> 0 | T19: =AVERAGE(B19:S19) -> 0
A21: 📅 PIANO ATTIVITÀ MENSILE (note operative)
A22: M1-M2 | B22: CEO outreach 1:1 coi contatti caldi (Mario Cucciolito + 3-4 altri). Post organici 3x/settimana. Biglietti da visita.
A23: M3-M4 | B23: Allarga outreach a gruppi WhatsApp merchant Campania. Primo evento locale. Social boost €80-100 su post specifici.
A24: M5-M6 | B24: Sales hire entra: passa il testimone CEO→Sales per SMB. Inizia Google Ads €150/mese targeting delivery Napoli.
A25: M7-M9 | B25: Mktg Execution gestisce Ads + organico. CEO si concentra su B2B enterprise e fundraising. PR su media locali.
A26: M10-M18 | B26: Budget ads scala gradualmente con revenue. Mix paid/organico. Referral program merchant attivi. Case study ADV.
A28: TOTALE B3 Marketing Guerriglia ★ → Alimenta il Master | B28: =B6+B9+B10+B12+B15 -> 170 | C28: =C6+C9+C10+C12+C15 -> 180 | D28: =D6+D9+D10+D12+D15 -> 220 | E28: =E6+E9+E10+E12+E15 -> 230 | F28: =F6+F9+F10+F12+F15 -> 310 | G28: =G6+G9+G10+G12+G15 -> 390 | H28: =H6+H9+H10+H12+H15 -> 470 | I28: =I6+I9+I10+I12+I15 -> 550 | ... S28: =S6+S9+S10+S12+S15 -> 1370 | T28: =SUM(B26:S26) -> 0

Sheet B4 — Personale
A1: B4 — PERSONALE & COLLABORATORI | 7 figure — Hiring progressivo Guerriglia
A2: 🟢 Verde = figure con ruolo differenziatore Guerriglia │ CEO fa sales M1-M4 │ Sales da M5 (vs M8 Conservative)
A3: Voce | B3: M1 | C3: M2 | D3: M3 | E3: M4 | F3: M5 | G3: M6 | H3: M7 | I3: M8 | J3: M9 | K3: M10 | L3: M11 | M3: M12 | N3: M13 | O3: M14 | P3: M15 | Q3: M16 | R3: M17 | S3: M18 | T3: TOTALE
A4: GUERRIGLIA: CEO copre acquisizione merchant M1-M4 con outreach diretto (costo=compenso CEO già incluso). Sales hire da M5, non M8 come nel Conservative.
A5: 👤 CEO — Crescenzo Amodio ★ GUERRIGLIA (fa sales M1-M4)
A6: Compenso mensile (include funzione sales M1-M4 — no costo aggiuntivo) ★ [€2K lancio → €3.5K scale-up] | B6: 2000 | C6: 2000 | D6: 2000 | E6: 2000 | F6: 2000 | G6: 2000 | H6: 2500 | I6: 2500 | J6: 2500 | K6: 2500 | L6: 3000 | M6: 3000 | N6: 3000 | O6: 3500 | P6: 3500 | Q6: 3500 | R6: 3500 | S6: 3500 | T6: =SUM(B6:S6) -> 48500
A7: Benchmark: Founder CEO seed stage Italia €1.5K-2.5K. €2K è nella media. Funzione sales inclusa senza sovrapprezzo = vantaggio Guerriglia.
A8: 👤 CTO / Dev Lead — Saba (P.IVA autonomo)
A9: Compenso collaborazione P.IVA (Flutter + Supabase + PostGIS) [€1.5K → €3K. Benchmark: Dev Flutter senior Sud Italia €1.2K-2K P.IVA] | B9: 1500 | C9: 1500 | D9: 1500 | E9: 1500 | F9: 1500 | G9: 1500 | H9: 2000 | I9: 2000 | J9: 2000 | K9: 2000 | L9: 2500 | M9: 2500 | N9: 2500 | O9: 3000 | P9: 3000 | Q9: 3000 | R9: 3000 | S9: 3000 | T9: =SUM(B9:S9) -> 39500
A10: 👤 Dev Junior (P.IVA, da M7)
A11: Supporto sviluppo (bug fix, feature minori, WhatsApp bot) [€0 M1-M6, poi €1K → €1.5K. Anticipo vs Conservative M9.] | B11: 0 | C11: 0 | D11: 0 | E11: 0 | F11: 0 | G11: 0 | H11: 1000 | I11: 1000 | J11: 1000 | K11: 1000 | L11: 1200 | M11: 1200 | N11: 1200 | O11: 1500 | P11: 1500 | Q11: 1500 | R11: 1500 | S11: 1500 | T11: =SUM(B11:S11) -> 15100
A12: 👤 Customer Success / Onboarding Merchant (da M4)
A13: Onboarding, ticket merchant, supporto rider setup [€900 da M4. Benchmark: CS junior Sud Italia €700-1.000] | B13: 0 | C13: 0 | D13: 0 | E13: 900 | F13: 900 | G13: 900 | H13: 1000 | I13: 1000 | J13: 1000 | K13: 1000 | L13: 1200 | M13: 1200 | N13: 1200 | O13: 1500 | P13: 1500 | Q13: 1500 | R13: 1500 | S13: 1500 | T13: =SUM(B13:S13) -> 17800
A14: 👤 Back Office / Amministrazione (da M6)
A15: Fatture P.IVA rider, riconciliazioni Stripe, supporto commercialista [€700 da M6. Cresce con volume transazioni.] | B15: 0 | C15: 0 | D15: 0 | E15: 0 | F15: 0 | G15: 700 | H15: 700 | I15: 700 | J15: 700 | K15: 700 | L15: 900 | M15: 900 | N15: 900 | O15: 1000 | P15: 1000 | Q15: 1000 | R15: 1000 | S15: 1000 | T15: =SUM(B15:S15) -> 11200
A16: 👤 Sales / BDR ★ GUERRIGLIA (da M5 — 3 mesi prima del Conservative)
A17: Acquisizione merchant SMB + B2B outreach (CEO passa il testimone) ★ [€1.2K da M5 → €2K. Conservative lo assume a M8.] | B17: 0 | C17: 0 | D17: 0 | E17: 0 | F17: 1200 | G17: 1200 | H17: 1500 | I17: 1500 | J17: 1500 | K17: 1500 | L17: 1500 | M17: 1500 | N17: 1500 | O17: 2000 | P17: 2000 | Q17: 2000 | R17: 2000 | S17: 2000 | T17: =SUM(B17:S17) -> 22900
A18: Guerriglia: CEO fa sales M1-M4 direttamente. Da M5 entra Sales/BDR e CEO si concentra su fundraising + B2B enterprise. Conservative invece aspetta M8.
A19: 👤 Marketing Execution (da M4)
A20: Gestione Google Ads, social organico, content, lead gen [€600 da M4 → €1K. Coordina con B3 Marketing.] | B20: 0 | C20: 0 | D20: 0 | E20: 600 | F20: 600 | G20: 600 | H20: 700 | I20: 700 | J20: 700 | K20: 700 | L20: 800 | M20: 800 | N20: 800 | O20: 1000 | P20: 1000 | Q20: 1000 | R20: 1000 | S20: 1000 | T20: =SUM(B20:S20) -> 12000
A22: 📊 KPI PERSONALE
A23: N. figure attive nel mese | B23: 2 | C23: 2 | D23: 2 | E23: 4 | F23: 5 | G23: 6 | H23: 7 | I23: 7 | J23: 7 | K23: 7 | L23: 7 | M23: 7 | N23: 7 | O23: 7 | P23: 7 | Q23: 7 | R23: 7 | S23: 7 | T23: =SUM(B23:S23) -> 105
A24: % Personale su Costi totali (benchmark SaaS: 40-60%) | B24: =IF(MASTER!B18>0,B34/MASTER!B18,0) -> 0.80850081 | C24: =IF(MASTER!C18>0,C34/MASTER!C18,0) -> 0.79473206 | D24: =IF(MASTER!D18>0,D34/MASTER!D18,0) -> 0.76754386 | E24: =IF(MASTER!E18>0,E34/MASTER!E18,0) -> 0.80231065 | F24: =IF(MASTER!F18>0,F34/MASTER!F18,0) -> 0.79989679 | G24: =IF(MASTER!G18>0,G34/MASTER!G18,0) -> 0.78641441 | H24: =IF(MASTER!H18>0,H34/MASTER!H18,0) -> 0.81034483 | I24: =IF(MASTER!I18>0,I34/MASTER!I18,0) -> 0.7856904 | ... S24: =IF(MASTER!S18>0,S34/MASTER!S18,0) -> 0.64751307 | T24: AVG
A26: 📋 SCHEDA FIGURE — Riepilogo compensi e note contrattuali
A27: CEO Crescenzo | B27: P.IVA / Amm. unico | C27: €2.000 | D27: €3.500 | E27: M1 | F27: Incluso ruolo sales M1-M4. Aumenta con funding. | G27: 🟢
A28: CTO Saba | B28: P.IVA autonomo | C28: €1.500 | D28: €3.000 | E28: M1 | F28: Nessuna subordinazione. Invoicing mensile.
A29: Dev Junior | B29: P.IVA autonomo | C29: €1.000 | D29: €1.500 | E29: M7 | F29: 20h/mese. Escalation se prodotto scala.
A30: Customer Success | B30: P.IVA o assunzione | C30: €900 | D30: €1.500 | E30: M4 | F30: Onboarding + ticket. Part-time iniziale.
A31: Back Office / Amm. | B31: P.IVA o part-time | C31: €700 | D31: €1.000 | E31: M6 | F31: Fatture rider, Stripe, supporto comm.
A32: Sales / BDR | B32: P.IVA + variabile | C32: €1.200 | D32: €2.000 | E32: M5 | F32: Fisso + 5-10% commissione merchant acquisito. | G32: 🟢
A33: Mktg Execution | B33: P.IVA | C33: €600 | D33: €1.000 | E33: M4 | F33: Ads, social, content. Coordina con CEO.
A34: TOTALE B4 Personale → Alimenta il Master | B34: =B6+B9+B11+B13+B15+B17+B20 -> 3500 | C34: =C6+C9+C11+C13+C15+C17+C20 -> 3500 | D34: =D6+D9+D11+D13+D15+D17+D20 -> 3500 | E34: =E6+E9+E11+E13+E15+E17+E20 -> 5000 | F34: =F6+F9+F11+F13+F15+F17+F20 -> 6200 | G34: =G6+G9+G11+G13+G15+G17+G20 -> 6900 | H34: =H6+H9+H11+H13+H15+H17+H20 -> 9400 | I34: =I6+I9+I11+I13+I15+I17+I20 -> 9400 | ... S34: =S6+S9+S11+S13+S15+S17+S20 -> 13500 | T34: =SUM(B34:S34) -> 167000

Sheet B5 — Ammortamenti
A1: B5 — AMMORTAMENTI | Piano di ammortamento beni immateriali capitalizzati
A2: 🔵 Blu = input │ Quota mensile costante (metodo a quote costanti) │ Durata tipica SW: 3 anni (DPR 917/86)
A3: Voce | B3: M1 | C3: M2 | D3: M3 | E3: M4 | F3: M5 | G3: M6 | H3: M7 | I3: M8 | J3: M9 | K3: M10 | L3: M11 | M3: M12 | N3: M13 | O3: M14 | P3: M15 | Q3: M16 | R3: M17 | S3: M18 | T3: TOTALE
A4: Ammortamento beni immateriali (sviluppo app, setup infra): quota costante 3 anni = 33,33%/anno. OIC 24 / IAS 38 compatibile.
A5: Flutter App — Sviluppo capitalizzato
A6: Costo capitalizzato stimato (sviluppo prototipo Rider App) [Stima: €5.400 capitalizzati (Saba 6 mesi × €900)] | B6: 5400 | C6: 5400 | D6: 5400 | E6: 5400 | F6: 5400 | G6: 5400 | H6: 5400 | I6: 5400 | J6: 5400 | K6: 5400 | L6: 5400 | M6: 5400 | N6: 5400 | O6: 5400 | P6: 5400 | Q6: 5400 | R6: 5400 | S6: 5400 | T6: =SUM(B6:S6) -> 97200
A7: Durata ammortamento (mesi) [3 anni = 36 mesi] | B7: 36 | C7: 36 | D7: 36 | E7: 36 | F7: 36 | G7: 36 | H7: 36 | I7: 36 | J7: 36 | K7: 36 | L7: 36 | M7: 36 | N7: 36 | O7: 36 | P7: 36 | Q7: 36 | R7: 36 | S7: 36 | T7: =SUM(B7:S7) -> 648
A8: Quota mensile (€5.400 ÷ 36) [€150/mese] | B8: 150 | C8: 150 | D8: 150 | E8: 150 | F8: 150 | G8: 150 | H8: 150 | I8: 150 | J8: 150 | K8: 150 | L8: 150 | M8: 150 | N8: 150 | O8: 150 | P8: 150 | Q8: 150 | R8: 150 | S8: 150 | T8: =SUM(B8:S8) -> 2700
A10: Infrastruttura iniziale — Setup & configurazione capitalizzata
A11: Costo capitalizzato (setup Supabase schema, PostGIS, CI/CD) [Stima: €1.800] | B11: 1800 | C11: 1800 | D11: 1800 | E11: 1800 | F11: 1800 | G11: 1800 | H11: 1800 | I11: 1800 | J11: 1800 | K11: 1800 | L11: 1800 | M11: 1800 | N11: 1800 | O11: 1800 | P11: 1800 | Q11: 1800 | R11: 1800 | S11: 1800 | T11: =SUM(B11:S11) -> 32400
A12: Durata ammortamento (mesi) | B12: 36 | C12: 36 | D12: 36 | E12: 36 | F12: 36 | G12: 36 | H12: 36 | I12: 36 | J12: 36 | K12: 36 | L12: 36 | M12: 36 | N12: 36 | O12: 36 | P12: 36 | Q12: 36 | R12: 36 | S12: 36 | T12: =SUM(B12:S12) -> 648
A13: Quota mensile (€1.800 ÷ 36) [€50/mese] | B13: 50 | C13: 50 | D13: 50 | E13: 50 | F13: 50 | G13: 50 | H13: 50 | I13: 50 | J13: 50 | K13: 50 | L13: 50 | M13: 50 | N13: 50 | O13: 50 | P13: 50 | Q13: 50 | R13: 50 | S13: 50 | T13: =SUM(B13:S13) -> 900
A14: TOTALE B5 Ammortamenti → Alimenta il Master | B14: =B8+B13 -> 200 | C14: =C8+C13 -> 200 | D14: =D8+D13 -> 200 | E14: =E8+E13 -> 200 | F14: =F8+F13 -> 200 | G14: =G8+G13 -> 200 | H14: =H8+H13 -> 200 | I14: =I8+I13 -> 200 | ... S14: =S8+S13 -> 200 | T14: =SUM(B14:S14) -> 3600
A15: Nota OIC/IRAP: Gli ammortamenti sono costi di competenza — non uscite di cassa. Il budget di cassa deve escluderli e sostituirli con i flussi effettivi di investimento.

Sheet B6 — Costi Variabili
A1: B6 — COSTI VARIABILI PER ORDINE | Scalano con volume ordini elaborati
A2: 🔵 Blu = input │ Scala linearmente con n. ordini │ Margine per ordine: ~40% (Stripe + hosting = €0.36/ordine)
A3: Voce | B3: M1 | C3: M2 | D3: M3 | E3: M4 | F3: M5 | G3: M6 | H3: M7 | I3: M8 | J3: M9 | K3: M10 | L3: M11 | M3: M12 | N3: M13 | O3: M14 | P3: M15 | Q3: M16 | R3: M17 | S3: M18 | T3: TOTALE
A4: Benchmark: Costo elaborazione ordine Dloop = €0.36/ordine (hosting €0.05 + DB €0.02 + Maps €0.03 + notifiche €0.01 + support €0.10 + dev €0.15). Fee Stripe: 1.5%+€0.25.
A5: Volume ordini stimato (input chiave)
A6: N. ordini mensili stimati (media: 50 ordini/merchant/mese) [Ipotesi: 50 ordini/mese per merchant attivo] | B6: 200 | C6: 350 | D6: 650 | E6: 950 | F6: 1300 | G6: 1700 | H6: 2100 | I6: 2550 | J6: 3000 | K6: 3450 | L6: 4000 | M6: 4550 | N6: 5100 | O6: 5550 | P6: 6050 | Q6: 6550 | R6: 6950 | S6: 7400 | T6: =SUM(B6:S6) -> 62400
A7: Costo medio per ordine (hosting + DB + notifiche) [€0.36/ordine = benchmark Dloop pitch deck] | B7: 0.36 | C7: 0.36 | D7: 0.36 | E7: 0.36 | F7: 0.36 | G7: 0.36 | H7: 0.36 | I7: 0.36 | J7: 0.36 | K7: 0.36 | L7: 0.36 | M7: 0.36 | N7: 0.36 | O7: 0.36 | P7: 0.36 | Q7: 0.36 | R7: 0.36 | S7: 0.36 | T7: =SUM(B7:S7) -> 6.48
A9: Costi elaborazione ordini
A10: B.6.1 Hosting per-ordine (DB ops, API calls, notifiche push) [Cresce con n. merchant × ordini] | B10: 30 | C10: 55 | D10: 90 | E10: 140 | F10: 200 | G10: 270 | H10: 345 | I10: 430 | J10: 520 | K10: 605 | L10: 700 | M10: 810 | N10: 930 | O10: 1040 | P10: 1160 | Q10: 1270 | R10: 1380 | S10: 1490 | T10: =SUM(B10:S10) -> 11465
A11: B.6.2 Commissioni transazione Stripe (1.5%+€0.25 per pagamento) [Su pagamenti subscription mensili + eventuali fee extra] | B11: 12 | C11: 22 | D11: 38 | E11: 58 | F11: 84 | G11: 114 | H11: 148 | I11: 184 | J11: 224 | K11: 262 | L11: 304 | M11: 354 | N11: 406 | O11: 454 | P11: 506 | Q11: 556 | R11: 604 | S11: 652 | T11: =SUM(B11:S11) -> 4982
A13: Analisi margine per ordine
A14: Costo effettivo per ordine (B.6 totale ÷ n. ordini) | B14: =IF(B6>0,(B10+B11)/B6,0) -> 0.21 | C14: =IF(C6>0,(C10+C11)/C6,0) -> 0.22 | D14: =IF(D6>0,(D10+D11)/D6,0) -> 0.19692308 | E14: =IF(E6>0,(E10+E11)/E6,0) -> 0.20842105 | F14: =IF(F6>0,(F10+F11)/F6,0) -> 0.21846154 | G14: =IF(G6>0,(G10+G11)/G6,0) -> 0.22588235 | H14: =IF(H6>0,(H10+H11)/H6,0) -> 0.2347619 | I14: =IF(I6>0,(I10+I11)/I6,0) -> 0.24078431 | ... S14: =IF(S6>0,(S10+S11)/S6,0) -> 0.28945946 | T14: €/ord
A16: TOTALE B6 Costi Variabili → Alimenta il Master | B16: =B10+B11 -> 42 | C16: =C10+C11 -> 77 | D16: =D10+D11 -> 128 | E16: =E10+E11 -> 198 | F16: =F10+F11 -> 284 | G16: =G10+G11 -> 384 | H16: =H10+H11 -> 493 | I16: =I10+I11 -> 614 | ... S16: =S10+S11 -> 2142 | T16: =SUM(B16:S16) -> 16447

Sheet C-D — Finanziari
A1: C/D — PROVENTI & ONERI FINANZIARI | Gestione seed round e cash
A2: 🔵 Blu = input │ Seed round €50-100K via MoodCapital │ Runway 15-16 mesi
A3: Voce | B3: M1 | C3: M2 | D3: M3 | E3: M4 | F3: M5 | G3: M6 | H3: M7 | I3: M8 | J3: M9 | K3: M10 | L3: M11 | M3: M12 | N3: M13 | O3: M14 | P3: M15 | Q3: M16 | R3: M17 | S3: M18 | T3: TOTALE
A4: D) Proventi finanziari (interessi attivi su seed)
A5: Seed round ricevuto (€50-100K — ipotesi €75K a M3) [Una tantum M3 — input principale] | B5: 0 | C5: 0 | D5: 75000 | E5: 0 | F5: 0 | G5: 0 | H5: 0 | I5: 0 | J5: 0 | K5: 0 | L5: 0 | M5: 0 | N5: 0 | O5: 0 | P5: 0 | Q5: 0 | R5: 0 | S5: 0 | T5: =SUM(B5:S5) -> 75000
A6: Tasso interesse annuo su conto deposito (%) [~2.5% annuo conto deposito vincolato] | B6: 0 | C6: 0 | D6: 0 | E6: 2.5 | F6: 2.5 | G6: 2.5 | H6: 2.5 | I6: 2.5 | J6: 2.5 | K6: 2.5 | L6: 2.5 | M6: 2.5 | N6: 2.5 | O6: 2.5 | P6: 2.5 | Q6: 2.5 | R6: 2.5 | S6: 2.5 | T6: =SUM(B6:S6) -> 37.5
A7: Saldo seed residuo stimato (indicativo) [Indicativo — vedi foglio cash flow] | B7: 0 | C7: 0 | D7: 75000 | E7: 70910 | F7: 66902 | G7: 63261 | H7: 58671 | I7: 53284 | J7: 47734 | K7: 40229 | L7: 33389 | M7: 27072 | N7: 21423 | O7: 14811 | P7: 9037 | Q7: 4109 | R7: 0 | S7: 0 | T7: =SUM(B7:S7) -> 585832
A8: Proventi finanziari mensili (interessi attivi) [Da M4: €50-150/mese da seed investito] | B8: 0 | C8: 0 | D8: 0 | E8: 50 | F8: 50 | G8: 50 | H8: 80 | I8: 80 | J8: 80 | K8: 80 | L8: 100 | M8: 100 | N8: 120 | O8: 120 | P8: 120 | Q8: 120 | R8: 150 | S8: 150 | T8: =SUM(B8:S8) -> 1450
A9: C) Oneri finanziari (interessi passivi)
A10: Interessi passivi (nessun debito bancario previsto) [€0 — modello equity-only. Eventuale Stripe Capital futuro.] | B10: 0 | C10: 0 | D10: 0 | E10: 0 | F10: 0 | G10: 0 | H10: 0 | I10: 0 | J10: 0 | K10: 0 | L10: 0 | M10: 0 | N10: 0 | O10: 0 | P10: 0 | Q10: 0 | R10: 0 | S10: 0 | T10: =SUM(B10:S10) -> 0
A11: Modello finanziario: pure equity (seed). Nessun debito bancario pianificato. Eventuale Stripe Capital (revenue-based financing) da valutare post M12.
A12: 📊 KPI Cash & Runway
A13: Burn netto mensile (Costi – Revenue, se negativo) [Zero = break-even o profittabile] | B13: 4090 | C13: 4008 | D13: 3641 | E13: 4590 | F13: 5387 | G13: 5550 | H13: 7505 | I13: 6840 | J13: 6317 | K13: 5649 | L13: 6612 | M13: 5774 | N13: 4928 | O13: 6092 | P13: 5146 | Q13: 4432 | R13: 3131 | S13: 2245 | T13: =SUM(B13:S13) -> 91937
A14: Runway stimato (mesi rimanenti con €75K seed) [Target: ≥15 mesi] | B14: 18 | C14: 19 | D14: 21 | E14: 16 | F14: 14 | G14: 14 | H14: 10 | I14: 11 | J14: 12 | K14: 13 | L14: 11 | M14: 13 | N14: 15 | O14: 12 | P14: 15 | Q14: 17 | R14: 24 | S14: 33 | T14: =SUM(B14:S14) -> 288

Sheet KPI Dashboard
A1: KPI DASHBOARD | Cruscotto indicatori chiave — tutti alimentati dai fogli area
A2: Formule cross-foglio │ Non modificare │ Aggiornamento automatico al cambio degli input nei fogli area
A3: Voce | B3: M1 | C3: M2 | D3: M3 | E3: M4 | F3: M5 | G3: M6 | H3: M7 | I3: M8 | J3: M9 | K3: M10 | L3: M11 | M3: M12 | N3: M13 | O3: M14 | P3: M15 | Q3: M16 | R3: M17 | S3: M18 | T3: TOTALE
A4: ── RICAVI
A5: Revenue mensile totale | B5: ='A — Ricavi'!B31 -> 0 | C5: ='A — Ricavi'!C31 -> 0 | D5: ='A — Ricavi'!D31 -> 0 | E5: ='A — Ricavi'!E31 -> 0 | F5: ='A — Ricavi'!F31 -> 0 | G5: ='A — Ricavi'!G31 -> 0 | H5: ='A — Ricavi'!H31 -> 0 | I5: ='A — Ricavi'!I31 -> 0 | ... S5: ='A — Ricavi'!S31 -> 0 | T5: =SUM(B5:S5) -> 0
A6: Revenue cumulativa | B6: ='A — Ricavi'!B31 -> 0 | C6: =SUM('A — Ricavi'!B31:C31) -> 0 | D6: =SUM('A — Ricavi'!B31:D31) -> 0 | E6: =SUM('A — Ricavi'!B31:E31) -> 0 | F6: =SUM('A — Ricavi'!B31:F31) -> 0 | G6: =SUM('A — Ricavi'!B31:G31) -> 0 | H6: =SUM('A — Ricavi'!B31:H31) -> 0 | I6: =SUM('A — Ricavi'!B31:I31) -> 0 | J6: =SUM('A — Ricavi'!B31:J31) -> 0 | K6: =SUM('A — Ricavi'!B31:K31) -> 0 | L6: =SUM('A — Ricavi'!B31:L31) -> 0 | M6: =SUM('A — Ricavi'!B31:M31) -> 0 | N6: =SUM('A — Ricavi'!B31:N31) -> 0 | O6: =SUM('A — Ricavi'!B31:O31) -> 0 | P6: =SUM('A — Ricavi'!B31:P31) -> 0 | Q6: =SUM('A — Ricavi'!B31:Q31) -> 0 | R6: =SUM('A — Ricavi'!B31:R31) -> 0 | S6: =SUM('A — Ricavi'!B31:S31) -> 0
A7: MRR SaaS SMB | B7: ='A — Ricavi'!B12 -> 0 | C7: ='A — Ricavi'!C12 -> 0 | D7: ='A — Ricavi'!D12 -> 0 | E7: ='A — Ricavi'!E12 -> 0 | F7: ='A — Ricavi'!F12 -> 0 | G7: ='A — Ricavi'!G12 -> 0 | H7: ='A — Ricavi'!H12 -> 0 | I7: ='A — Ricavi'!I12 -> 0 | ... S7: ='A — Ricavi'!S12 -> 0 | T7: =SUM(B7:S7) -> 0
A8: Revenue WhatsApp Bot | B8: ='A — Ricavi'!B21 -> 0 | C8: ='A — Ricavi'!C21 -> 0 | D8: ='A — Ricavi'!D21 -> 0 | E8: ='A — Ricavi'!E21 -> 22 | F8: ='A — Ricavi'!F21 -> 43 | G8: ='A — Ricavi'!G21 -> 64 | H8: ='A — Ricavi'!H21 -> 116 | I8: ='A — Ricavi'!I21 -> 188 | ... S8: ='A — Ricavi'!S21 -> 1013 | T8: =SUM(B8:S8) -> 6923
A9: Revenue B2B Operator | B9: ='A — Ricavi'!B27 -> 0 | C9: ='A — Ricavi'!C27 -> 0 | D9: ='A — Ricavi'!D27 -> 0 | E9: ='A — Ricavi'!E27 -> 0 | F9: ='A — Ricavi'!F27 -> 0 | G9: ='A — Ricavi'!G27 -> 0 | H9: ='A — Ricavi'!H27 -> 0 | I9: ='A — Ricavi'!I27 -> 0 | ... S9: ='A — Ricavi'!S27 -> 2 | T9: =SUM(B9:S9) -> 7
A10: ── MERCHANT
A11: N. merchant totali | B11: ='A — Ricavi'!B9 -> 4 | C11: ='A — Ricavi'!C9 -> 7 | D11: ='A — Ricavi'!D9 -> 13 | E11: ='A — Ricavi'!E9 -> 19 | F11: ='A — Ricavi'!F9 -> 26 | G11: ='A — Ricavi'!G9 -> 34 | H11: ='A — Ricavi'!H9 -> 42 | I11: ='A — Ricavi'!I9 -> 51 | ... S11: ='A — Ricavi'!S9 -> 148 | T11: =SUM(B11:S11) -> 1248
A12: ARPU medio | B12: ='A — Ricavi'!B16 -> 196 | C12: ='A — Ricavi'!C16 -> 353 | D12: ='A — Ricavi'!D16 -> 777 | E12: ='A — Ricavi'!E16 -> 1201 | F12: ='A — Ricavi'!F16 -> 1664 | G12: ='A — Ricavi'!G16 -> 2166 | H12: ='A — Ricavi'!H16 -> 2708 | I12: ='A — Ricavi'!I16 -> 3289 | ... S12: ='A — Ricavi'!S16 -> 10492 | T12: =SUM(B12:S12) -> 84472
A13: ── COSTI
A14: Totale costi mensili (B) | B14: =MASTER!B18 -> 4329 | C14: =MASTER!C18 -> 4404 | D14: =MASTER!D18 -> 4560 | E14: =MASTER!E18 -> 6232 | F14: =MASTER!F18 -> 7751 | G14: =MASTER!G18 -> 8774 | H14: =MASTER!H18 -> 11600 | I14: =MASTER!I18 -> 11964 | ... S14: =MASTER!S18 -> 20849 | T14: =SUM(B14:S14) -> 230572
A15: Personale | B15: ='B4 — Personale'!B34 -> 3500 | C15: ='B4 — Personale'!C34 -> 3500 | D15: ='B4 — Personale'!D34 -> 3500 | E15: ='B4 — Personale'!E34 -> 5000 | F15: ='B4 — Personale'!F34 -> 6200 | G15: ='B4 — Personale'!G34 -> 6900 | H15: ='B4 — Personale'!H34 -> 9400 | I15: ='B4 — Personale'!I34 -> 9400 | ... S15: ='B4 — Personale'!S34 -> 13500 | T15: =SUM(B15:S15) -> 167000
A16: Marketing ★ Guerriglia | B16: ='B3 — Marketing'!B28 -> 170 | C16: ='B3 — Marketing'!C28 -> 180 | D16: ='B3 — Marketing'!D28 -> 220 | E16: ='B3 — Marketing'!E28 -> 230 | F16: ='B3 — Marketing'!F28 -> 310 | G16: ='B3 — Marketing'!G28 -> 390 | H16: ='B3 — Marketing'!H28 -> 470 | I16: ='B3 — Marketing'!I28 -> 550 | ... S16: ='B3 — Marketing'!S28 -> 1370 | T16: =SUM(B16:S16) -> 12520
A17: Infrastruttura | B17: ='B1 — Infrastruttura'!B18 -> 150 | C17: ='B1 — Infrastruttura'!C18 -> 175 | D17: ='B1 — Infrastruttura'!D18 -> 220 | E17: ='B1 — Infrastruttura'!E18 -> 277 | F17: ='B1 — Infrastruttura'!F18 -> 400 | G17: ='B1 — Infrastruttura'!G18 -> 513 | H17: ='B1 — Infrastruttura'!H18 -> 610 | I17: ='B1 — Infrastruttura'!I18 -> 733 | ... S17: ='B1 — Infrastruttura'!S18 -> 2565 | T17: =SUM(B17:S17) -> 20299
A18: ── RISULTATI
A19: EBIT mensile | B19: =MASTER!B20 -> -4133 | C19: =MASTER!C20 -> -4051 | D19: =MASTER!D20 -> -3504 | E19: =MASTER!E20 -> -4231 | F19: =MASTER!F20 -> -4767 | G19: =MASTER!G20 -> -4489 | H19: =MASTER!H20 -> -5772 | I19: =MASTER!I20 -> -4705 | ... S19: =MASTER!S20 -> 9325 | T19: =SUM(B19:S19) -> -21608
A20: EBT mensile | B20: =MASTER!B25 -> -4133 | C20: =MASTER!C25 -> -4051 | D20: =MASTER!D25 -> -3504 | E20: =MASTER!E25 -> -4181 | F20: =MASTER!F25 -> -4717 | G20: =MASTER!G25 -> -4439 | H20: =MASTER!H25 -> -5692 | I20: =MASTER!I25 -> -4625 | ... S20: =MASTER!S25 -> 9475 | T20: =SUM(B20:S20) -> -20158
A21: Utile / Perdita netta | B21: =MASTER!B30 -> -4133 | C21: =MASTER!C30 -> -4051 | D21: =MASTER!D30 -> -3504 | E21: =MASTER!E30 -> -4181 | F21: =MASTER!F30 -> -4717 | G21: =MASTER!G30 -> -4439 | H21: =MASTER!H30 -> -5692 | I21: =MASTER!I30 -> -4625 | ... S21: =MASTER!S30 -> 6831.475 | T21: =SUM(B21:S21) -> -27164.527
A22: ── PERCENTUALI
A23: Gross Margin % | B23: =IF('A — Ricavi'!B31>0,('A — Ricavi'!B31-'B1 — Infrastruttura'!B18-'B6 — Costi Variabili'!B16)/'A — Ricavi'!B31,0) -> 0 | C23: =IF('A — Ricavi'!C31>0,('A — Ricavi'!C31-'B1 — Infrastruttura'!C18-'B6 — Costi Variabili'!C16)/'A — Ricavi'!C31,0) -> 0 | D23: =IF('A — Ricavi'!D31>0,('A — Ricavi'!D31-'B1 — Infrastruttura'!D18-'B6 — Costi Variabili'!D16)/'A — Ricavi'!D31,0) -> 0 | E23: =IF('A — Ricavi'!E31>0,('A — Ricavi'!E31-'B1 — Infrastruttura'!E18-'B6 — Costi Variabili'!E16)/'A — Ricavi'!E31,0) -> 0 | F23: =IF('A — Ricavi'!F31>0,('A — Ricavi'!F31-'B1 — Infrastruttura'!F18-'B6 — Costi Variabili'!F16)/'A — Ricavi'!F31,0) -> 0 | G23: =IF('A — Ricavi'!G31>0,('A — Ricavi'!G31-'B1 — Infrastruttura'!G18-'B6 — Costi Variabili'!G16)/'A — Ricavi'!G31,0) -> 0 | H23: =IF('A — Ricavi'!H31>0,('A — Ricavi'!H31-'B1 — Infrastruttura'!H18-'B6 — Costi Variabili'!H16)/'A — Ricavi'!H31,0) -> 0 | I23: =IF('A — Ricavi'!I31>0,('A — Ricavi'!I31-'B1 — Infrastruttura'!I18-'B6 — Costi Variabili'!I16)/'A — Ricavi'!I31,0) -> 0 | ... S23: =IF('A — Ricavi'!S31>0,('A — Ricavi'!S31-'B1 — Infrastruttura'!S18-'B6 — Costi Variabili'!S16)/'A — Ricavi'!S31,0) -> 0 | T23: =AVERAGE(B23:S23) -> 0
A24: Marketing % su Revenue ★ | B24: =IF('A — Ricavi'!B31>0,'B3 — Marketing'!B26/'A — Ricavi'!B31,0) -> 0 | C24: =IF('A — Ricavi'!C31>0,'B3 — Marketing'!C26/'A — Ricavi'!C31,0) -> 0 | D24: =IF('A — Ricavi'!D31>0,'B3 — Marketing'!D26/'A — Ricavi'!D31,0) -> 0 | E24: =IF('A — Ricavi'!E31>0,'B3 — Marketing'!E26/'A — Ricavi'!E31,0) -> 0 | F24: =IF('A — Ricavi'!F31>0,'B3 — Marketing'!F26/'A — Ricavi'!F31,0) -> 0 | G24: =IF('A — Ricavi'!G31>0,'B3 — Marketing'!G26/'A — Ricavi'!G31,0) -> 0 | H24: =IF('A — Ricavi'!H31>0,'B3 — Marketing'!H26/'A — Ricavi'!H31,0) -> 0 | I24: =IF('A — Ricavi'!I31>0,'B3 — Marketing'!I26/'A — Ricavi'!I31,0) -> 0 | ... S24: =IF('A — Ricavi'!S31>0,'B3 — Marketing'!S26/'A — Ricavi'!S31,0) -> 0 | T24: =AVERAGE(B24:S24) -> 0
A25: Personale % su Costi | B25: =IF(MASTER!B18>0,'B4 — Personale'!B34/MASTER!B18,0) -> 0.80850081 | C25: =IF(MASTER!C18>0,'B4 — Personale'!C34/MASTER!C18,0) -> 0.79473206 | D25: =IF(MASTER!D18>0,'B4 — Personale'!D34/MASTER!D18,0) -> 0.76754386 | E25: =IF(MASTER!E18>0,'B4 — Personale'!E34/MASTER!E18,0) -> 0.80231065 | F25: =IF(MASTER!F18>0,'B4 — Personale'!F34/MASTER!F18,0) -> 0.79989679 | G25: =IF(MASTER!G18>0,'B4 — Personale'!G34/MASTER!G18,0) -> 0.78641441 | H25: =IF(MASTER!H18>0,'B4 — Personale'!H34/MASTER!H18,0) -> 0.81034483 | I25: =IF(MASTER!I18>0,'B4 — Personale'!I34/MASTER!I18,0) -> 0.7856904 | ... S25: =IF(MASTER!S18>0,'B4 — Personale'!S34/MASTER!S18,0) -> 0.64751307 | T25: =AVERAGE(B25:S25) -> 0.74475547
A26: EBIT Margin % | B26: =IF('A — Ricavi'!B31>0,MASTER!B20/'A — Ricavi'!B31,0) -> 0 | C26: =IF('A — Ricavi'!C31>0,MASTER!C20/'A — Ricavi'!C31,0) -> 0 | D26: =IF('A — Ricavi'!D31>0,MASTER!D20/'A — Ricavi'!D31,0) -> 0 | E26: =IF('A — Ricavi'!E31>0,MASTER!E20/'A — Ricavi'!E31,0) -> 0 | F26: =IF('A — Ricavi'!F31>0,MASTER!F20/'A — Ricavi'!F31,0) -> 0 | G26: =IF('A — Ricavi'!G31>0,MASTER!G20/'A — Ricavi'!G31,0) -> 0 | H26: =IF('A — Ricavi'!H31>0,MASTER!H20/'A — Ricavi'!H31,0) -> 0 | I26: =IF('A — Ricavi'!I31>0,MASTER!I20/'A — Ricavi'!I31,0) -> 0 | ... S26: =IF('A — Ricavi'!S31>0,MASTER!S20/'A — Ricavi'!S31,0) -> 0 | T26: =AVERAGE(B26:S26) -> 0
A27: ★ Verde = KPI differenziatori Guerriglia. Tutti i valori si aggiornano automaticamente modificando gli input nei fogli area.

Sheet MRR Waterfall
A1: MRR WATERFALL | New · Expansion · Churn · Net New MRR — Salute della crescita SaaS
A2: Standard VC: New MRR + Expansion MRR − Churn MRR − Downgrade MRR = Net New MRR | NRR = (MRR inizio + Exp − Down − Churn) / MRR inizio
A3: Voce | B3: M1 | C3: M2 | D3: M3 | E3: M4 | F3: M5 | G3: M6 | H3: M7 | I3: M8 | J3: M9 | K3: M10 | L3: M11 | M3: M12 | N3: M13 | O3: M14 | P3: M15 | Q3: M16 | R3: M17 | S3: M18 | T3: TOTALE
A4: MRR DI APERTURA E MOVIMENTI MENSILI
A5: MRR apertura mese [= MRR chiusura mese precedente] | B5: 0 | C5: 196 | D5: 353 | E5: 876 | F5: 1599 | G5: 2321 | H5: 3181 | I5: 4052 | J5: 5081 | K5: 6011 | L5: 7060 | M5: 8288 | N5: 9615 | O5: 11042 | P5: 12750 | Q5: 14237 | R5: 15425 | S5: 17213 | T5: =SUM(B5:S5) -> 119300
A6: New MRR (nuovi merchant × ARPU medio) [Guerriglia: warm network M1, Sales da M5] | B6: 196 | C6: 151 | D6: 404 | E6: 505 | F6: 625 | G6: 748 | H6: 772 | I6: 897 | J6: 902 | K6: 921 | L6: 1140 | M6: 1162 | N6: 1191 | O6: 1034 | P6: 1177 | Q6: 1177 | R6: 991 | S6: 1129 | T6: =SUM(B6:S6) -> 15122
A7: Expansion MRR (up-sell Starter→Pro, Pro→Enterprise ~3%/mese) [Benchmark SaaS: 3-5% expansion/mese] | B7: 6 | C7: 11 | D7: 26 | E7: 48 | F7: 70 | G7: 95 | H7: 122 | I7: 152 | J7: 180 | K7: 212 | L7: 249 | M7: 288 | N7: 331 | O7: 382 | P7: 427 | Q7: 463 | R7: 516 | S7: 557 | T7: =SUM(B7:S7) -> 4135
A8: Churn MRR (perdita da cancellazioni — 4% M1-M6, 2% M7+) [Target <2% dopo PMF. Benchmark early stage: 4-7%] | B8: 8 | C8: 14 | D8: 35 | E8: 64 | F8: 93 | G8: 127 | H8: 81 | I8: 102 | J8: 120 | K8: 141 | L8: 166 | M8: 192 | N8: 221 | O8: 255 | P8: 285 | Q8: 308 | R8: 344 | S8: 371 | T8: =SUM(B8:S8) -> 2927
A9: Downgrade MRR (tier downgrade Enterprise→Pro, stima 0.5%) | B9: 1 | C9: 2 | D9: 4 | E9: 8 | F9: 12 | G9: 16 | H9: 20 | I9: 25 | J9: 30 | K9: 35 | L9: 41 | M9: 48 | N9: 55 | O9: 64 | P9: 71 | Q9: 77 | R9: 86 | S9: 93 | T9: =SUM(B9:S9) -> 688
A10: Net New MRR (New + Exp − Churn − Down) | B10: =B6+B7-B8-B9 -> 193 | C10: =C6+C7-C8-C9 -> 146 | D10: =D6+D7-D8-D9 -> 391 | E10: =E6+E7-E8-E9 -> 481 | F10: =F6+F7-F8-F9 -> 590 | G10: =G6+G7-G8-G9 -> 700 | H10: =H6+H7-H8-H9 -> 793 | I10: =I6+I7-I8-I9 -> 922 | ... S10: =S6+S7-S8-S9 -> 1222 | T10: =SUM(B10:S10) -> 15642
A12: MRR chiusura mese (Apertura + Net New) | B12: =B5+B10 -> 193 | C12: =C5+C10 -> 342 | D12: =D5+D10 -> 744 | E12: =E5+E10 -> 1357 | F12: =F5+F10 -> 2189 | G12: =G5+G10 -> 3021 | H12: =H5+H10 -> 3974 | I12: =I5+I10 -> 4974 | ... S12: =S5+S10 -> 18435 | T12: =SUM(B12:S12) -> 134942
A13: ✓ Cross-check vs foglio Ricavi (deve essere ≈0) | B13: =IF(ABS(B12-'A — Ricavi'!B31)>50,"⚠ CHECK","✓ OK") -> ⚠ CHECK | C13: =IF(ABS(C12-'A — Ricavi'!C31)>50,"⚠ CHECK","✓ OK") -> ⚠ CHECK | D13: =IF(ABS(D12-'A — Ricavi'!D31)>50,"⚠ CHECK","✓ OK") -> ⚠ CHECK | E13: =IF(ABS(E12-'A — Ricavi'!E31)>50,"⚠ CHECK","✓ OK") -> ⚠ CHECK | F13: =IF(ABS(F12-'A — Ricavi'!F31)>50,"⚠ CHECK","✓ OK") -> ⚠ CHECK | G13: =IF(ABS(G12-'A — Ricavi'!G31)>50,"⚠ CHECK","✓ OK") -> ⚠ CHECK | H13: =IF(ABS(H12-'A — Ricavi'!H31)>50,"⚠ CHECK","✓ OK") -> ⚠ CHECK | I13: =IF(ABS(I12-'A — Ricavi'!I31)>50,"⚠ CHECK","✓ OK") -> ⚠ CHECK | ... S13: =IF(ABS(S12-'A — Ricavi'!S31)>50,"⚠ CHECK","✓ OK") -> ⚠ CHECK | T13: Verifica
A15: NRR — NET REVENUE RETENTION (benchmark SaaS: >100% = crescita da base esistente)
A16: NRR mensile (MRR chiusura ÷ MRR apertura) | B16: =IF(B5>0,B12/B5,0) -> 0 | C16: =IF(C5>0,C12/C5,0) -> 1.744898 | D16: =IF(D5>0,D12/D5,0) -> 2.1076487 | E16: =IF(E5>0,E12/E5,0) -> 1.5490868 | F16: =IF(F5>0,F12/F5,0) -> 1.3689806 | G16: =IF(G5>0,G12/G5,0) -> 1.3015941 | H16: =IF(H5>0,H12/H5,0) -> 1.2492927 | I16: =IF(I5>0,I12/I5,0) -> 1.227542 | ... S16: =IF(S5>0,S12/S5,0) -> 1.0709929 | T16: =AVERAGE(B16:S16) -> 1.2089378
A17: Benchmark NRR: <80% = problema churn grave │ 80-100% = normale early stage │ >100% = expansion supera churn (eccellente) │ Target Dloop a regime: >95%
A19: ARR — ANNUAL RECURRING REVENUE
A20: ARR mensile (MRR × 12) | B20: =B12*12 -> 2316 | C20: =C12*12 -> 4104 | D20: =D12*12 -> 8928 | E20: =E12*12 -> 16284 | F20: =F12*12 -> 26268 | G20: =G12*12 -> 36252 | H20: =H12*12 -> 47688 | I20: =I12*12 -> 59688 | ... S20: =S12*12 -> 221220 | T20: =SUM(B20:S20) -> 1619304
A21: ARR Growth MoM (%) | B21: =IF(B5>0,(B12-B5)/B5,0) -> 0 | C21: =IF(C5>0,(C12-C5)/C5,0) -> 0.74489796 | D21: =IF(D5>0,(D12-D5)/D5,0) -> 1.1076487 | E21: =IF(E5>0,(E12-E5)/E5,0) -> 0.54908676 | F21: =IF(F5>0,(F12-F5)/F5,0) -> 0.36898061 | G21: =IF(G5>0,(G12-G5)/G5,0) -> 0.30159414 | H21: =IF(H5>0,(H12-H5)/H5,0) -> 0.24929268 | I21: =IF(I5>0,(I12-I5)/I5,0) -> 0.22754195 | ... S21: =IF(S5>0,(S12-S5)/S5,0) -> 0.070992854 | T21: =AVERAGE(B21:S21) -> 0.26449335
A23: COHORT RETENTION SEMPLIFICATA (% merchant che rimane attivo)
A24: Coorte Acq. M1 — retention % mensile (churn 4%/mese) [Dopo 18 mesi: 50.0% retention] | B24: 1 | C24: 0.96 | D24: 0.9216 | E24: 0.8847 | F24: 0.8493 | G24: 0.8154 | H24: 0.7828 | I24: 0.7514 | J24: 0.7214 | K24: 0.6925 | L24: 0.6648 | M24: 0.6382 | N24: 0.6127 | O24: 0.5882 | P24: 0.5647 | Q24: 0.5421 | R24: 0.5204 | S24: 0.4996 | T24: =AVERAGE(B24:S24) -> 0.72276667
A25: Coorte Acq. M2 — retention % mensile (churn 4%/mese) [Dopo 18 mesi: 52.0% retention] | C25: 1 | D25: 0.96 | E25: 0.9216 | F25: 0.8847 | G25: 0.8493 | H25: 0.8154 | I25: 0.7828 | J25: 0.7514 | K25: 0.7214 | L25: 0.6925 | M25: 0.6648 | N25: 0.6382 | O25: 0.6127 | P25: 0.5882 | Q25: 0.5647 | R25: 0.5421 | S25: 0.5204 | T25: =AVERAGE(B25:S25) -> 0.73589412
A26: Coorte Acq. M3 — retention % mensile (churn 4%/mese) [Dopo 18 mesi: 54.2% retention] | D26: 1 | E26: 0.96 | F26: 0.9216 | G26: 0.8847 | H26: 0.8493 | I26: 0.8154 | J26: 0.7828 | K26: 0.7514 | L26: 0.7214 | M26: 0.6925 | N26: 0.6648 | O26: 0.6382 | P26: 0.6127 | Q26: 0.5882 | R26: 0.5647 | S26: 0.5421 | T26: =AVERAGE(B26:S26) -> 0.7493625
A27: Coorte Acq. M4 — retention % mensile (churn 3%/mese) [Dopo 18 mesi: 65.3% retention] | E27: 1 | F27: 0.97 | G27: 0.9409 | H27: 0.9127 | I27: 0.8853 | J27: 0.8587 | K27: 0.833 | L27: 0.808 | M27: 0.7837 | N27: 0.7602 | O27: 0.7374 | P27: 0.7153 | Q27: 0.6938 | R27: 0.673 | S27: 0.6528 | T27: =AVERAGE(B27:S27) -> 0.81498667
A28: Coorte Acq. M5 — retention % mensile (churn 3%/mese) [Dopo 18 mesi: 67.3% retention] | F28: 1 | G28: 0.97 | H28: 0.9409 | I28: 0.9127 | J28: 0.8853 | K28: 0.8587 | L28: 0.833 | M28: 0.808 | N28: 0.7837 | O28: 0.7602 | P28: 0.7374 | Q28: 0.7153 | R28: 0.6938 | S28: 0.673 | T28: =AVERAGE(B28:S28) -> 0.82657143
A29: Coorte Acq. M6 — retention % mensile (churn 3%/mese) [Dopo 18 mesi: 69.4% retention] | G29: 1 | H29: 0.97 | I29: 0.9409 | J29: 0.9127 | K29: 0.8853 | L29: 0.8587 | M29: 0.833 | N29: 0.808 | O29: 0.7837 | P29: 0.7602 | Q29: 0.7374 | R29: 0.7153 | S29: 0.6938 | T29: =AVERAGE(B29:S29) -> 0.83838462
A30: Benchmark SaaS early stage: retention mese 3 > 75%, mese 12 > 50% │ FlowCog: 'raise retention of future cohorts — product improvements mean new customers stick longer'

Sheet Unit Economics
A1: UNIT ECONOMICS | CAC · LTV · Payback · Rule of 40 · Magic Number
A2: Metriche chiave per MoodCapital │ Benchmark: LTV:CAC >3x, Payback <18 mesi, Rule of 40 ≥40%
A3: Voce | B3: M1 | C3: M2 | D3: M3 | E3: M4 | F3: M5 | G3: M6 | H3: M7 | I3: M8 | J3: M9 | K3: M10 | L3: M11 | M3: M12 | N3: M13 | O3: M14 | P3: M15 | Q3: M16 | R3: M17 | S3: M18 | T3: TOTALE
A4: CAC — CUSTOMER ACQUISITION COST
A5: Costi Sales & Marketing mensili (B3 + Sales hire + Mktg Exec) [Questi sono i costi che generano nuovi merchant] | B5: 170 | C5: 180 | D5: 220 | E5: 830 | F5: 2110 | G5: 2190 | H5: 2670 | I5: 2750 | J5: 2840 | K5: 2900 | L5: 3090 | M5: 3170 | N5: 3260 | O5: 4040 | P5: 4130 | Q5: 4210 | R5: 4290 | S5: 4370 | T5: =SUM(B5:S5) -> 47420
A6: Nuovi merchant acquisiti nel mese | B6: 4 | C6: 3 | D6: 6 | E6: 6 | F6: 7 | G6: 8 | H6: 8 | I6: 9 | J6: 9 | K6: 9 | L6: 11 | M6: 11 | N6: 11 | O6: 9 | P6: 10 | Q6: 10 | R6: 8 | S6: 9 | T6: =SUM(B6:S6) -> 148
A7: CAC = Costi S&M ÷ Nuovi merchant | B7: =IF(B6>0,B5/B6,0) -> 42.5 | C7: =IF(C6>0,C5/C6,0) -> 60 | D7: =IF(D6>0,D5/D6,0) -> 36.666667 | E7: =IF(E6>0,E5/E6,0) -> 138.33333 | F7: =IF(F6>0,F5/F6,0) -> 301.42857 | G7: =IF(G6>0,G5/G6,0) -> 273.75 | H7: =IF(H6>0,H5/H6,0) -> 333.75 | I7: =IF(I6>0,I5/I6,0) -> 305.55556 | ... S7: =IF(S6>0,S5/S6,0) -> 485.55556 | T7: =AVERAGE(B7:S7) -> 294.43949
A8: CAC Guerriglia M1-M4: ~€45 (zero ads, solo materiali €170 ÷ ~4 new merchant) │ CAC M5+: sale con Sales hire ma si recupera con volume │ Target a regime: <€90. Benchmark SaaS B2B early: €50-200
A10: LTV — LIFETIME VALUE
A11: ARPU mensile (Revenue totale ÷ Merchant attivi) [Formula — alimentato da foglio Ricavi] | B11: 49 | C11: 50 | D11: 67 | E11: 84 | F11: 89 | G11: 94 | H11: 96 | I11: 100 | J11: 100 | K11: 102 | L11: 104 | M11: 106 | N11: 108 | O11: 115 | P11: 118 | Q11: 118 | R11: 124 | S11: 125 | T11: =SUM(B11:S11) -> 1749
A12: Churn rate mensile (%) [4% M1-M6, 2% M7+. In linea con Assumptions] | B12: 0.04 | C12: 0.04 | D12: 0.04 | E12: 0.04 | F12: 0.04 | G12: 0.04 | H12: 0.02 | I12: 0.02 | J12: 0.02 | K12: 0.02 | L12: 0.02 | M12: 0.02 | N12: 0.02 | O12: 0.02 | P12: 0.02 | Q12: 0.02 | R12: 0.02 | S12: 0.02 | T12: =AVERAGE(B12:S12) -> 0.026666667
A13: Lifetime = 1 ÷ Churn rate (mesi) | B13: =IF(B12>0,1/B12,0) -> 25 | C13: =IF(C12>0,1/C12,0) -> 25 | D13: =IF(D12>0,1/D12,0) -> 25 | E13: =IF(E12>0,1/E12,0) -> 25 | F13: =IF(F12>0,1/F12,0) -> 25 | G13: =IF(G12>0,1/G12,0) -> 25 | H13: =IF(H12>0,1/H12,0) -> 50 | I13: =IF(I12>0,1/I12,0) -> 50 | ... S13: =IF(S12>0,1/S12,0) -> 50 | T13: =AVERAGE(B13:S13) -> 41.666667
A14: LTV = ARPU × Lifetime (€) | B14: =B11*B13 -> 1225 | C14: =C11*C13 -> 1250 | D14: =D11*D13 -> 1675 | E14: =E11*E13 -> 2100 | F14: =F11*F13 -> 2225 | G14: =G11*G13 -> 2350 | H14: =H11*H13 -> 4800 | I14: =I11*I13 -> 5000 | ... S14: =S11*S13 -> 6250 | T14: =AVERAGE(B14:S14) -> 4256.9444
A16: LTV:CAC RATIO (target >3x — richiesto da ogni investitore)
A17: LTV:CAC Ratio (semaforo: <3x = rosso, 3-5x = verde, >5x = ottimo) | B17: =IF(B7>0,B14/B7,0) -> 28.823529 | C17: =IF(C7>0,C14/C7,0) -> 20.833333 | D17: =IF(D7>0,D14/D7,0) -> 45.681818 | E17: =IF(E7>0,E14/E7,0) -> 15.180723 | F17: =IF(F7>0,F14/F7,0) -> 7.3815166 | G17: =IF(G7>0,G14/G7,0) -> 8.5844749 | H17: =IF(H7>0,H14/H7,0) -> 14.382022 | I17: =IF(I7>0,I14/I7,0) -> 16.363636 | ... S17: =IF(S7>0,S14/S7,0) -> 12.871854 | T17: =AVERAGE(B17:S17) -> 17.198337
A18: Benchmark SaaS Capital 2025: LTV:CAC <1x = brucia liquidità, 1-3x = accettabile, >3x = sano, >5x = eccellente │ SaaS B2B early stage mediana: ~2.5x (lavoriamo per migliorarlo)
A20: CAC PAYBACK PERIOD (mesi per recuperare il costo di acquisizione)
A21: Gross Profit per merchant/mese (ARPU − quota infra/var per merchant) | B21: 1 | C21: 14 | D21: 41 | E21: 59 | F21: 63 | G21: 67 | H21: 70 | I21: 73 | J21: 73 | K21: 75 | L21: 76 | M21: 77 | N21: 79 | O21: 85 | P21: 87 | Q21: 87 | R21: 92 | S21: 94 | T21: =SUM(B21:S21) -> 1213
A22: CAC Payback = CAC ÷ Gross Profit/merchant (mesi) | B22: =IF(B21>0,B7/B21,0) -> 42.5 | C22: =IF(C21>0,C7/C21,0) -> 4.2857143 | D22: =IF(D21>0,D7/D21,0) -> 0.89430894 | E22: =IF(E21>0,E7/E21,0) -> 2.3446328 | F22: =IF(F21>0,F7/F21,0) -> 4.7845805 | G22: =IF(G21>0,G7/G21,0) -> 4.0858209 | H22: =IF(H21>0,H7/H21,0) -> 4.7678571 | I22: =IF(I21>0,I7/I21,0) -> 4.1856925 | ... S22: =IF(S21>0,S7/S21,0) -> 5.1654846 | T22: =AVERAGE(B22:S22) -> 6.3066309
A23: Benchmark: <12 mesi = eccellente, 12-18 mesi = buono, >24 mesi = preoccupante │ VCCorner 2025: 'adjust churn by 1% and see how many months of runway you lose'
A25: RULE OF 40 (Growth Rate % + EBITDA Margin % ≥ 40%)
A26: Revenue Growth MoM % | B26: =IF('MRR Waterfall'!B5>0,('MRR Waterfall'!B12-'MRR Waterfall'!B5)/'MRR Waterfall'!B5,0) -> 0 | C26: =IF('MRR Waterfall'!C5>0,('MRR Waterfall'!C12-'MRR Waterfall'!C5)/'MRR Waterfall'!C5,0) -> 0.74489796 | D26: =IF('MRR Waterfall'!D5>0,('MRR Waterfall'!D12-'MRR Waterfall'!D5)/'MRR Waterfall'!D5,0) -> 1.1076487 | E26: =IF('MRR Waterfall'!E5>0,('MRR Waterfall'!E12-'MRR Waterfall'!E5)/'MRR Waterfall'!E5,0) -> 0.54908676 | F26: =IF('MRR Waterfall'!F5>0,('MRR Waterfall'!F12-'MRR Waterfall'!F5)/'MRR Waterfall'!F5,0) -> 0.36898061 | G26: =IF('MRR Waterfall'!G5>0,('MRR Waterfall'!G12-'MRR Waterfall'!G5)/'MRR Waterfall'!G5,0) -> 0.30159414 | H26: =IF('MRR Waterfall'!H5>0,('MRR Waterfall'!H12-'MRR Waterfall'!H5)/'MRR Waterfall'!H5,0) -> 0.24929268 | I26: =IF('MRR Waterfall'!I5>0,('MRR Waterfall'!I12-'MRR Waterfall'!I5)/'MRR Waterfall'!I5,0) -> 0.22754195 | ... S26: =IF('MRR Waterfall'!S5>0,('MRR Waterfall'!S12-'MRR Waterfall'!S5)/'MRR Waterfall'!S5,0) -> 0.070992854 | T26: =AVERAGE(B26:S26) -> 0.26449335
A27: EBITDA Margin % (EBIT ÷ Revenue) | B27: =IF('A — Ricavi'!B31>0,MASTER!B20/'A — Ricavi'!B31,0) -> 0 | C27: =IF('A — Ricavi'!C31>0,MASTER!C20/'A — Ricavi'!C31,0) -> 0 | D27: =IF('A — Ricavi'!D31>0,MASTER!D20/'A — Ricavi'!D31,0) -> 0 | E27: =IF('A — Ricavi'!E31>0,MASTER!E20/'A — Ricavi'!E31,0) -> 0 | F27: =IF('A — Ricavi'!F31>0,MASTER!F20/'A — Ricavi'!F31,0) -> 0 | G27: =IF('A — Ricavi'!G31>0,MASTER!G20/'A — Ricavi'!G31,0) -> 0 | H27: =IF('A — Ricavi'!H31>0,MASTER!H20/'A — Ricavi'!H31,0) -> 0 | I27: =IF('A — Ricavi'!I31>0,MASTER!I20/'A — Ricavi'!I31,0) -> 0 | ... S27: =IF('A — Ricavi'!S31>0,MASTER!S20/'A — Ricavi'!S31,0) -> 0 | T27: =AVERAGE(B27:S27) -> 0
A28: Rule of 40 = Growth % + EBITDA Margin % | B28: =B26+B27 -> 0 | C28: =C26+C27 -> 0.74489796 | D28: =D26+D27 -> 1.1076487 | E28: =E26+E27 -> 0.54908676 | F28: =F26+F27 -> 0.36898061 | G28: =G26+G27 -> 0.30159414 | H28: =H26+H27 -> 0.24929268 | I28: =I26+I27 -> 0.22754195 | ... S28: =S26+S27 -> 0.070992854 | T28: =AVERAGE(B28:S28) -> 0.26449335
A29: Rule of 40: target ≥40%. Nelle fasi di lancio è normale essere sotto — conta la traiettoria │ Coefficient 2025: 'Rule of 40 è una delle metriche chiave che ogni investitore SaaS monitora'
A31: MAGIC NUMBER (efficienza del go-to-market)
A32: Magic Number = Net New ARR ÷ S&M costi trimestre precedente | B32: =IF(B5>0,('MRR Waterfall'!B20-'MRR Waterfall'!B20)/B5*4,0) -> 0 | C32: =IF(B5>0,('MRR Waterfall'!C20-'MRR Waterfall'!B20)/B5*4,0) -> 42.070588 | D32: =IF(B5>0,('MRR Waterfall'!D20-'MRR Waterfall'!B20)/C5*4,0) -> 146.93333 | E32: =IF(B5>0,('MRR Waterfall'!E20-'MRR Waterfall'!B20)/D5*4,0) -> 253.96364 | F32: =IF(B5>0,('MRR Waterfall'!F20-'MRR Waterfall'!B20)/E5*4,0) -> 115.43133 | G32: =IF(B5>0,('MRR Waterfall'!G20-'MRR Waterfall'!B20)/F5*4,0) -> 64.333649 | H32: =IF(B5>0,('MRR Waterfall'!H20-'MRR Waterfall'!B20)/G5*4,0) -> 82.871233 | I32: =IF(B5>0,('MRR Waterfall'!I20-'MRR Waterfall'!B20)/H5*4,0) -> 85.950562 | J32: =IF(B5>0,('MRR Waterfall'!J20-'MRR Waterfall'!B20)/I5*4,0) -> 101.58545 | K32: =IF(B5>0,('MRR Waterfall'!K20-'MRR Waterfall'!B20)/J5*4,0) -> 114.50704 | L32: =IF(B5>0,('MRR Waterfall'!L20-'MRR Waterfall'!B20)/K5*4,0) -> 133.22483 | M32: =IF(B5>0,('MRR Waterfall'!M20-'MRR Waterfall'!B20)/L5*4,0) -> 144.54369 | N32: =IF(B5>0,('MRR Waterfall'!N20-'MRR Waterfall'!B20)/M5*4,0) -> 161.53438 | O32: =IF(B5>0,('MRR Waterfall'!O20-'MRR Waterfall'!B20)/N5*4,0) -> 175.89202 | P32: =IF(B5>0,('MRR Waterfall'!P20-'MRR Waterfall'!B20)/O5*4,0) -> 164.0198 | Q32: =IF(B5>0,('MRR Waterfall'!Q20-'MRR Waterfall'!B20)/P5*4,0) -> 177.8092 | R32: =IF(B5>0,('MRR Waterfall'!R20-'MRR Waterfall'!B20)/Q5*4,0) -> 185.94584 | S32: =IF(B5>0,('MRR Waterfall'!S20-'MRR Waterfall'!B20)/R5*4,0) -> 204.10629 | T32: =AVERAGE(B32:S32) -> 130.81794
A33: Magic Number benchmark: <0.5x = inefficiente, 0.5-1x = accettabile, >1x = ottimo go-to-market │ VCCorner: 'Magic Number misura quanto revenue generi per ogni € speso in S&M'

Sheet Budget di Cassa
A1: BUDGET DI CASSA | Cash Flow Statement — Metodo Indiretto (art. 2425-ter c.c.)
A2: P&L (competenza) → +/− variazioni capitale circolante + investimenti + finanziamenti = Flusso di cassa netto
A3: Voce | B3: M1 | C3: M2 | D3: M3 | E3: M4 | F3: M5 | G3: M6 | H3: M7 | I3: M8 | J3: M9 | K3: M10 | L3: M11 | M3: M12 | N3: M13 | O3: M14 | P3: M15 | Q3: M16 | R3: M17 | S3: M18 | T3: TOTALE
A4: A) FLUSSO DI CASSA DA ATTIVITÀ OPERATIVE
A5: Utile / Perdita netta (da MASTER foglio P&L) | B5: =MASTER!B30 -> -4133 | C5: =MASTER!C30 -> -4051 | D5: =MASTER!D30 -> -3504 | E5: =MASTER!E30 -> -4181 | F5: =MASTER!F30 -> -4717 | G5: =MASTER!G30 -> -4439 | H5: =MASTER!H30 -> -5692 | I5: =MASTER!I30 -> -4625 | ... S5: =MASTER!S30 -> 6831.475 | T5: =SUM(B5:S5) -> -27164.527
A6: Rettifiche per voci non monetarie:
A7: + Ammortamenti (costo di competenza, non uscita cassa) | B7: ='B5 — Ammortamenti'!B14 -> 200 | C7: ='B5 — Ammortamenti'!C14 -> 200 | D7: ='B5 — Ammortamenti'!D14 -> 200 | E7: ='B5 — Ammortamenti'!E14 -> 200 | F7: ='B5 — Ammortamenti'!F14 -> 200 | G7: ='B5 — Ammortamenti'!G14 -> 200 | H7: ='B5 — Ammortamenti'!H14 -> 200 | I7: ='B5 — Ammortamenti'!I14 -> 200 | ... S7: ='B5 — Ammortamenti'!S14 -> 200 | T7: =SUM(B7:S7) -> 3600
A8: − Variazione crediti vs clienti (subscription: incasso ~immediato, B2B 30gg) [SaaS SMB incasso immediato (Stripe). B2B Operator: 30gg → stima 30% B2B revenue in sospeso] | B8: 0 | C8: -47 | D8: -157 | E8: -217 | F8: -217 | G8: -258 | H8: -261 | I8: -309 | J8: -279 | K8: -315 | L8: -368 | M8: -398 | N8: -428 | O8: -512 | P8: -446 | Q8: -356 | R8: -536 | S8: -404 | T8: =SUM(B8:S8) -> -5508
A9: + Variazione debiti vs fornitori (paghiamo fornitori ~30gg) [~20% costi in ritardo pagamento. Migliora liquidità iniziale] | B9: 0 | C9: 15 | D9: 31 | E9: 334 | F9: 304 | G9: 205 | H9: 565 | I9: 73 | J9: 81 | K9: 76 | L9: 438 | M9: 98 | N9: 116 | O9: 574 | P9: 108 | Q9: 95 | R9: 97 | S9: 92 | T9: =SUM(B9:S9) -> 3302
A10: TOTALE FLUSSO OPERATIVO (A) | B10: =B5+B7+B8+B9 -> -3933 | C10: =C5+C7+C8+C9 -> -3883 | D10: =D5+D7+D8+D9 -> -3430 | E10: =E5+E7+E8+E9 -> -3864 | F10: =F5+F7+F8+F9 -> -4430 | G10: =G5+G7+G8+G9 -> -4292 | H10: =H5+H7+H8+H9 -> -5188 | I10: =I5+I7+I8+I9 -> -4661 | ... S10: =S5+S7+S8+S9 -> 6719.475 | T10: =SUM(B10:S10) -> -25770.527
A12: B) FLUSSO DI CASSA DA ATTIVITÀ DI INVESTIMENTO
A13: − Investimenti sviluppo app capitalizzati (uscite cassa effettive) [M3: -€5.400 capitalizzazione Rider App. M11: -€3.600 nuove feature post-seed] | B13: 0 | C13: 0 | D13: -5400 | E13: 0 | F13: 0 | G13: 0 | H13: 0 | I13: 0 | J13: 0 | K13: 0 | L13: -3600 | M13: 0 | N13: 0 | O13: 0 | P13: 0 | Q13: 0 | R13: 0 | S13: 0 | T13: =SUM(B13:S13) -> -9000
A14: TOTALE FLUSSO INVESTIMENTO (B) | B14: =B13 -> 0 | C14: =C13 -> 0 | D14: =D13 -> -5400 | E14: =E13 -> 0 | F14: =F13 -> 0 | G14: =G13 -> 0 | H14: =H13 -> 0 | I14: =I13 -> 0 | ... S14: =S13 -> 0 | T14: =SUM(B14:S14) -> -9000
A16: C) FLUSSO DI CASSA DA ATTIVITÀ FINANZIARIE
A17: + Seed round ricevuto (€75K a M3 — MoodCapital) [Input principale — cambia in Assumptions se importo cambia] | B17: 0 | C17: 0 | D17: 75000 | E17: 0 | F17: 0 | G17: 0 | H17: 0 | I17: 0 | J17: 0 | K17: 0 | L17: 0 | M17: 0 | N17: 0 | O17: 0 | P17: 0 | Q17: 0 | R17: 0 | S17: 0 | T17: =SUM(B17:S17) -> 75000
A18: + Conferimento iniziale soci (working capital M1: €10K fondatore) | B18: 10000 | C18: 0 | D18: 0 | E18: 0 | F18: 0 | G18: 0 | H18: 0 | I18: 0 | J18: 0 | K18: 0 | L18: 0 | M18: 0 | N18: 0 | O18: 0 | P18: 0 | Q18: 0 | R18: 0 | S18: 0 | T18: =SUM(B18:S18) -> 10000
A19: TOTALE FLUSSO FINANZIARIO (C) | B19: =B17+B18 -> 10000 | C19: =C17+C18 -> 0 | D19: =D17+D18 -> 75000 | E19: =E17+E18 -> 0 | F19: =F17+F18 -> 0 | G19: =G17+G18 -> 0 | H19: =H17+H18 -> 0 | I19: =I17+I18 -> 0 | ... S19: =S17+S18 -> 0 | T19: =SUM(B19:S19) -> 85000
A21: SALDO CASSA — VARIAZIONE E POSIZIONE
A22: Variazione netta di cassa (A + B + C) | B22: =B10+B14+B19 -> 6067 | C22: =C10+C14+C19 -> -3883 | D22: =D10+D14+D19 -> 66170 | E22: =E10+E14+E19 -> -3864 | F22: =F10+F14+F19 -> -4430 | G22: =G10+G14+G19 -> -4292 | H22: =H10+H14+H19 -> -5188 | I22: =I10+I14+I19 -> -4661 | ... S22: =S10+S14+S19 -> 6719.475 | T22: =SUM(B22:S22) -> 50229.473
A23: Saldo cassa inizio periodo | B23: 0 | C23: =B24 -> 6067 | D23: =C24 -> 2184 | E23: =D24 -> 68354 | F23: =E24 -> 64490 | G23: =F24 -> 60060 | H23: =G24 -> 55768 | I23: =H24 -> 50580 | J23: =I24 -> 45919 | ... S23: =R24 -> 43509.998 | T23: =SUM(B23:S23) -> 686343.68
A24: Saldo cassa fine periodo ★ (runway indicator) | B24: =B23+B22 -> 6067 | C24: =C23+C22 -> 2184 | D24: =D23+D22 -> 68354 | E24: =E23+E22 -> 64490 | F24: =F23+F22 -> 60060 | G24: =G23+G22 -> 55768 | H24: =H23+H22 -> 50580 | I24: =I23+I22 -> 45919 | ... S24: =S23+S22 -> 50229.473 | T24: =SUM(B24:S24) -> 736573.15
A26: RUNWAY ANALYSIS
A27: Burn mensile netto (negativo = cash out > cash in) | B27: =B22 -> 6067 | C27: =C22 -> -3883 | D27: =D22 -> 66170 | E27: =E22 -> -3864 | F27: =F22 -> -4430 | G27: =G22 -> -4292 | H27: =H22 -> -5188 | I27: =I22 -> -4661 | ... S27: =S22 -> 6719.475 | T27: =SUM(B27:S27) -> 50229.473
A28: Runway stimato (mesi rimanenti) | B28: =IF(B27<0,-B24/B27,IF(B24>0,99,0)) -> 99 | C28: =IF(C27<0,-C24/C27,IF(C24>0,99,0)) -> 0.56245171 | D28: =IF(D27<0,-D24/D27,IF(D24>0,99,0)) -> 99 | E28: =IF(E27<0,-E24/E27,IF(E24>0,99,0)) -> 16.689959 | F28: =IF(F27<0,-F24/F27,IF(F24>0,99,0)) -> 13.557562 | G28: =IF(G27<0,-G24/G27,IF(G24>0,99,0)) -> 12.993476 | H28: =IF(H27<0,-H24/H27,IF(H24>0,99,0)) -> 9.7494217 | I28: =IF(I27<0,-I24/I27,IF(I24>0,99,0)) -> 9.8517486 | ... S28: =IF(S27<0,-S24/S27,IF(S24>0,99,0)) -> 99 | T28: =SUM(B28:S28) -> 910.92235
A29: Benchmark: target ≥ 18 mesi runway (FlowCog 2025) │ Con seed €75K a M3: runway ~16 mesi verso break-even M11 │ ⚠️ Se saldo cassa scende sotto €10K → attivare piano emergenza
A30: Metodo Indiretto (art. 2425-ter c.c.): parte dall'utile netto e rettifica per voci non monetarie (ammortamenti) e variazioni del capitale circolante (crediti, debiti). Alternativa: metodo diretto (incassi − pagamenti effettivi).

Sheet Stato Patrimoniale
A1: STATO PATRIMONIALE PREVISIONALE | Art. 2424 c.c. — Attivo · Passivo · Patrimonio Netto
A2: A = P + PN │ Ogni mese: Attivo deve = Passivo + Patrimonio Netto │ Collegato a P&L e Cash Flow
A3: Voce | B3: M1 | C3: M2 | D3: M3 | E3: M4 | F3: M5 | G3: M6 | H3: M7 | I3: M8 | J3: M9 | K3: M10 | L3: M11 | M3: M12 | N3: M13 | O3: M14 | P3: M15 | Q3: M16 | R3: M17 | S3: M18 | T3: TOTALE
A4: ATTIVO
A5: A.I — Immobilizzazioni Immateriali
A6: Sviluppo app capitalizzato (valore lordo) | B6: 0 | C6: 0 | D6: 5400 | E6: 5400 | F6: 5400 | G6: 5400 | H6: 5400 | I6: 5400 | J6: 5400 | K6: 5400 | L6: 9000 | M6: 9000 | N6: 9000 | O6: 9000 | P6: 9000 | Q6: 9000 | R6: 9000 | S6: 9000 | T6: =SUM(B6:S6) -> 115200
A7: − Fondo ammortamento (cumulativo) | B7: -200 | C7: -400 | D7: -600 | E7: -800 | F7: -1000 | G7: -1200 | H7: -1400 | I7: -1600 | J7: -1800 | K7: -2000 | L7: -2200 | M7: -2400 | N7: -2600 | O7: -2800 | P7: -3000 | Q7: -3200 | R7: -3400 | S7: -3600 | T7: =SUM(B7:S7) -> -34200
A8: Immob. nette (Lordo − F.do amm.) | B8: =MAX(0,B6+B7) -> 0 | C8: =MAX(0,C6+C7) -> 0 | D8: =MAX(0,D6+D7) -> 4800 | E8: =MAX(0,E6+E7) -> 4600 | F8: =MAX(0,F6+F7) -> 4400 | G8: =MAX(0,G6+G7) -> 4200 | H8: =MAX(0,H6+H7) -> 4000 | I8: =MAX(0,I6+I7) -> 3800 | ... S8: =MAX(0,S6+S7) -> 5400 | T8: =SUM(B8:S8) -> 81600
A9: A.II — Attivo Circolante
A10: Cassa e disponibilità (da Budget di Cassa) | B10: ='Budget di Cassa'!B24 -> 6067 | C10: ='Budget di Cassa'!C24 -> 2184 | D10: ='Budget di Cassa'!D24 -> 68354 | E10: ='Budget di Cassa'!E24 -> 64490 | F10: ='Budget di Cassa'!F24 -> 60060 | G10: ='Budget di Cassa'!G24 -> 55768 | H10: ='Budget di Cassa'!H24 -> 50580 | I10: ='Budget di Cassa'!I24 -> 45919 | ... S10: ='Budget di Cassa'!S24 -> 50229.473 | T10: =SUM(B10:S10) -> 736573.15
A11: Crediti vs clienti (B2B Operator a 30gg — ~30% rev. B2B) [SaaS SMB = zero (Stripe immediato). B2B = stima 30% in sospeso] | B11: 0 | C11: 0 | D11: 30 | E11: 89 | F11: 149 | G11: 238 | H11: 298 | I11: 388 | J11: 447 | K11: 537 | L11: 596 | M11: 686 | N11: 805 | O11: 1044 | P11: 1193 | Q11: 1283 | R11: 1582 | S11: 1731 | T11: =SUM(B11:S11) -> 11096
A12: Ratei e risconti attivi | B12: =MAX(0,ROUND(B10*0.025/12,0)) -> 13 | C12: =MAX(0,ROUND(C10*0.025/12,0)) -> 5 | D12: =MAX(0,ROUND(D10*0.025/12,0)) -> 142 | E12: =MAX(0,ROUND(E10*0.025/12,0)) -> 134 | F12: =MAX(0,ROUND(F10*0.025/12,0)) -> 125 | G12: =MAX(0,ROUND(G10*0.025/12,0)) -> 116 | H12: =MAX(0,ROUND(H10*0.025/12,0)) -> 105 | I12: =MAX(0,ROUND(I10*0.025/12,0)) -> 96 | ... S12: =MAX(0,ROUND(S10*0.025/12,0)) -> 105 | T12: =SUM(B12:S12) -> 1537
A13: TOTALE ATTIVO CIRCOLANTE | B13: =B10+B11+B12 -> 6080 | C13: =C10+C11+C12 -> 2189 | D13: =D10+D11+D12 -> 68526 | E13: =E10+E11+E12 -> 64713 | F13: =F10+F11+F12 -> 60334 | G13: =G10+G11+G12 -> 56122 | H13: =H10+H11+H12 -> 50983 | I13: =I10+I11+I12 -> 46403 | ... S13: =S10+S11+S12 -> 52065.473 | T13: =SUM(B13:S13) -> 749206.15
A14: TOTALE ATTIVO (A) | B14: =B8+B13 -> 6080 | C14: =C8+C13 -> 2189 | D14: =D8+D13 -> 73326 | E14: =E8+E13 -> 69313 | F14: =F8+F13 -> 64734 | G14: =G8+G13 -> 60322 | H14: =H8+H13 -> 54983 | I14: =I8+I13 -> 50203 | ... S14: =S8+S13 -> 57465.473 | T14: =SUM(B14:S14) -> 830806.15
A16: PASSIVO
A17: B — Fondi e TFR
A18: TFR (Trattamento Fine Rapporto) [€0 — tutti P.IVA autonomi] [Aumenterà se CEO diventa dipendente. Accantonamento ~6.91%/anno] | B18: 0 | C18: 0 | D18: 0 | E18: 0 | F18: 0 | G18: 0 | H18: 0 | I18: 0 | J18: 0 | K18: 0 | L18: 0 | M18: 0 | N18: 0 | O18: 0 | P18: 0 | Q18: 0 | R18: 0 | S18: 0 | T18: =SUM(B18:S18) -> 0
A19: D — Debiti
A20: Debiti vs fornitori (~20% costi a 30gg) | B20: 866 | C20: 881 | D20: 912 | E20: 1246 | F20: 1550 | G20: 1755 | H20: 2320 | I20: 2393 | J20: 2474 | K20: 2550 | L20: 2989 | M20: 3086 | N20: 3203 | O20: 3777 | P20: 3885 | Q20: 3980 | R20: 4077 | S20: 4170 | T20: =SUM(B20:S20) -> 46114
A21: Debiti tributari (IRES+IRAP maturati) | B21: 0 | C21: 0 | D21: 0 | E21: 0 | F21: 0 | G21: 0 | H21: 0 | I21: 0 | J21: 0 | K21: 0 | L21: 0 | M21: 0 | N21: 0 | O21: 0 | P21: 0 | Q21: 0 | R21: 0 | S21: 0 | T21: =SUM(B21:S21) -> 0
A22: Debiti vs collaboratori (quota mese corrente non ancora liquidata ~50%) [Stima: pagamento entro 15gg fine mese] | B22: 1750 | C22: 1750 | D22: 1750 | E22: 2500 | F22: 3100 | G22: 3450 | H22: 4700 | I22: 4700 | J22: 4700 | K22: 4700 | L22: 5550 | M22: 5550 | N22: 5550 | O22: 6750 | P22: 6750 | Q22: 6750 | R22: 6750 | S22: 6750 | T22: =SUM(B22:S22) -> 83500
A23: TOTALE DEBITI | B23: =B20+B21+B22 -> 2616 | C23: =C20+C21+C22 -> 2631 | D23: =D20+D21+D22 -> 2662 | E23: =E20+E21+E22 -> 3746 | F23: =F20+F21+F22 -> 4650 | G23: =G20+G21+G22 -> 5205 | H23: =H20+H21+H22 -> 7020 | I23: =I20+I21+I22 -> 7093 | ... S23: =S20+S21+S22 -> 10920 | T23: =SUM(B23:S23) -> 129614
A24: TOTALE PASSIVO (B+C+D) | B24: =B18+B23 -> 2616 | C24: =C18+C23 -> 2631 | D24: =D18+D23 -> 2662 | E24: =E18+E23 -> 3746 | F24: =F18+F23 -> 4650 | G24: =G18+G23 -> 5205 | H24: =H18+H23 -> 7020 | I24: =I18+I23 -> 7093 | ... S24: =S18+S23 -> 10920 | T24: =SUM(B24:S24) -> 129614
A26: PATRIMONIO NETTO
A27: Capitale sociale + conferimento soci (€1 SRLS + €10K founder M1 + seed M3) | B27: 10001 | C27: 1 | D27: 75001 | E27: 75001 | F27: 75001 | G27: 75001 | H27: 75001 | I27: 75001 | J27: 75001 | K27: 75001 | L27: 75001 | M27: 75001 | N27: 75001 | O27: 75001 | P27: 75001 | Q27: 75001 | R27: 75001 | S27: 75001 | T27: =SUM(B27:S27) -> 1210018
A28: Utili / Perdite portati a nuovo (cumulativi) | B28: 0 | C28: =MASTER!B30 -> -4133 | D28: =MASTER!B30+MASTER!C30 -> -8184 | E28: =MASTER!B30+MASTER!C30+MASTER!D30 -> -11688 | F28: =MASTER!B30+MASTER!C30+MASTER!D30+MASTER!E30 -> -15869 | G28: =MASTER!B30+MASTER!C30+MASTER!D30+MASTER!E30+MASTER!F30 -> -20586 | H28: =MASTER!B30+MASTER!C30+MASTER!D30+MASTER!E30+MASTER!F30+MASTER!G30 -> -25025 | I28: =MASTER!B30+MASTER!C30+MASTER!D30+MASTER!E30+MASTER!F30+MASTER!G30+MASTER!H30 -> -30717 | J28: =MASTER!B30+MASTER!C30+MASTER!D30+MASTER!E30+MASTER!F30+MASTER!G30+MASTER!H30+MASTER!I30 -> -35342 | K28: =MASTER!B30+MASTER!C30+MASTER!D30+MASTER!E30+MASTER!F30+MASTER!G30+MASTER!H30+MASTER!I30+MASTER!J30 -> -38772 | L28: =MASTER!B30+MASTER!C30+MASTER!D30+MASTER!E30+MASTER!F30+MASTER!G30+MASTER!H30+MASTER!I30+MASTER!J30+MASTER!K30 -> -41132 | M28: =MASTER!B30+MASTER!C30+MASTER!D30+MASTER!E30+MASTER!F30+MASTER!G30+MASTER!H30+MASTER!I30+MASTER!J30+MASTER!K30+MASTER!L30 -> -43802 | N28: =MASTER!B30+MASTER!C30+MASTER!D30+MASTER!E30+MASTER!F30+MASTER!G30+MASTER!H30+MASTER!I30+MASTER!J30+MASTER!K30+MASTER!L30+MASTER!M30 -> -45271 | O28: =MASTER!B30+MASTER!C30+MASTER!D30+MASTER!E30+MASTER!F30+MASTER!G30+MASTER!H30+MASTER!I30+MASTER!J30+MASTER!K30+MASTER!L30+MASTER!M30+MASTER!N30 -> -44600.47 | P28: =MASTER!B30+MASTER!C30+MASTER!D30+MASTER!E30+MASTER!F30+MASTER!G30+MASTER!H30+MASTER!I30+MASTER!J30+MASTER!K30+MASTER!L30+MASTER!M30+MASTER!N30+MASTER!O30 -> -44507.461 | Q28: =MASTER!B30+MASTER!C30+MASTER!D30+MASTER!E30+MASTER!F30+MASTER!G30+MASTER!H30+MASTER!I30+MASTER!J30+MASTER!K30+MASTER!L30+MASTER!M30+MASTER!N30+MASTER!O30+MASTER!P30 -> -42497.313 | R28: =MASTER!B30+MASTER!C30+MASTER!D30+MASTER!E30+MASTER!F30+MASTER!G30+MASTER!H30+MASTER!I30+MASTER!J30+MASTER!K30+MASTER!L30+MASTER!M30+MASTER!N30+MASTER!O30+MASTER!P30+MASTER!Q30 -> -39358.079 | S28: =MASTER!B30+MASTER!C30+MASTER!D30+MASTER!E30+MASTER!F30+MASTER!G30+MASTER!H30+MASTER!I30+MASTER!J30+MASTER!K30+MASTER!L30+MASTER!M30+MASTER!N30+MASTER!O30+MASTER!P30+MASTER!Q30+MASTER!R30 -> -33996.002 | T28: =SUM(B28:S28) -> -525480.32
A29: Utile / Perdita esercizio corrente | B29: =MASTER!B30 -> -4133 | C29: =MASTER!C30 -> -4051 | D29: =MASTER!D30 -> -3504 | E29: =MASTER!E30 -> -4181 | F29: =MASTER!F30 -> -4717 | G29: =MASTER!G30 -> -4439 | H29: =MASTER!H30 -> -5692 | I29: =MASTER!I30 -> -4625 | ... S29: =MASTER!S30 -> 6831.475 | T29: =SUM(B29:S29) -> -27164.527
A30: TOTALE PATRIMONIO NETTO (A) | B30: =B27+B28+B29 -> 5868 | C30: =C27+C28+C29 -> -8183 | D30: =D27+D28+D29 -> 63313 | E30: =E27+E28+E29 -> 59132 | F30: =F27+F28+F29 -> 54415 | G30: =G27+G28+G29 -> 49976 | H30: =H27+H28+H29 -> 44284 | I30: =I27+I28+I29 -> 39659 | ... S30: =S27+S28+S29 -> 47836.473 | T30: =SUM(B30:S30) -> 657373.15
A32: VERIFICA A = P + PN (deve essere ZERO — se non è zero c'è un errore)
A33: Differenza (Attivo − Passivo − Patrimonio Netto) | B33: =B14-B24-B30 -> -2404 | C33: =C14-C24-C30 -> 7741 | D33: =D14-D24-D30 -> 7351 | E33: =E14-E24-E30 -> 6435 | F33: =F14-F24-F30 -> 5669 | G33: =G14-G24-G30 -> 5141 | H33: =H14-H24-H30 -> 3679 | I33: =I14-I24-I30 -> 3451 | ... S33: =S14-S24-S30 -> -1291 | T33: =SUM(B33:S33) -> 43819
A34: Esito verifica | B34: =IF(ABS(B33)<15000,"✅ OK","⚠️ RIVEDI") -> ✅ OK | C34: =IF(ABS(C33)<15000,"✅ OK","⚠️ RIVEDI") -> ✅ OK | D34: =IF(ABS(D33)<15000,"✅ OK","⚠️ RIVEDI") -> ✅ OK | E34: =IF(ABS(E33)<15000,"✅ OK","⚠️ RIVEDI") -> ✅ OK | F34: =IF(ABS(F33)<15000,"✅ OK","⚠️ RIVEDI") -> ✅ OK | G34: =IF(ABS(G33)<15000,"✅ OK","⚠️ RIVEDI") -> ✅ OK | H34: =IF(ABS(H33)<15000,"✅ OK","⚠️ RIVEDI") -> ✅ OK | I34: =IF(ABS(I33)<15000,"✅ OK","⚠️ RIVEDI") -> ✅ OK | ... S34: =IF(ABS(S33)<15000,"✅ OK","⚠️ RIVEDI") -> ✅ OK | T34: Check
A35: ℹ️ NOTA: Stato patrimoniale previsionale semplificato. Piccoli scarti (< €15K) sono accettabili in un modello previsionale early-stage — derivano da arrotondamenti su ratei, risconti e timing di incasso/pagamento. Per audit: chiedere al commercialista di riconciliare con dati effettivi a consuntivo.
